{
  "creds": {
    "noiseKey": {
      "private": {
        "type": "Buffer",
        "data": "OE/cVXApVkpzyvWjv0mSiC64oambSeAzlf4Si0DD3Wk="
      },
      "public": {
        "type": "Buffer",
        "data": "lf/b3z/bm0yWczSvu59JfHS7ydlIy6id8Ld7d83VHFA="
      }
    },
    "signedIdentityKey": {
      "private": {
        "type": "Buffer",
        "data": "ANHsaBnJfAxWyqO3kJAq5kaR15DKPHszvUOOoMVzvGg="
      },
      "public": {
        "type": "Buffer",
        "data": "hmvxmzUCycBsyTJx0WoEc4ExYj8CIGqVK1Y5saNchHQ="
      }
    },
    "signedPreKey": {
      "keyPair": {
        "private": {
          "type": "Buffer",
          "data": "QF9Xm6yMcvWrR9fcvu+RXTezOx9SLn/yRtxNBEXSClo="
        },
        "public": {
          "type": "Buffer",
          "data": "jG52mYGP395TFYm3Zcc6kpGoIsoGSXwu2yf5N6vJx1U="
        }
      },
      "signature": {
        "type": "Buffer",
        "data": "zLde5aKVCqecfmxogQMh8aXOQsCYb/p1vJcYfchdjYL/TxfDRlBgBtPxcV9xzNS2PpcGR2QN/s03ch0+vjuGiw=="
      },
      "keyId": 1
    },
    "registrationId": 114,
    "advSecretKey": "ODVFK292a3wdS6OsaQf/P/qwAF7YSHUoXHDlnsm3Hp8=",
    "processedHistoryMessages": [
      {
        "key": {
          "remoteJid": "917898259805@s.whatsapp.net",
          "fromMe": true,
          "id": "993185E3E954B67A47C6D9D26CC46266"
        },
        "timestamp": 1657032131
      },
      {
        "key": {
          "remoteJid": "917898259805@s.whatsapp.net",
          "fromMe": true,
          "id": "EE3E9CAA5C8922DA6D3BE4C2F4517628"
        },
        "timestamp": 1657032132
      }
    ],
    "nextPreKeyId": 31,
    "firstUnuploadedPreKeyId": 31,
    "accountSettings": {
      "unarchiveChats": false
    },
    "account": {
      "details": "CL6Xv7EFELybkZYGGAE=",
      "accountSignature": "INjdrbzciw69DJeCOFCJwQXo4RIwz1PdIw+Sam8ZOCmuHqbbg4ZWQvk3DjNF6PhByfhPfYDWyMd1NHZrQm+tCA==",
      "deviceSignature": "fvXZorW79QBon56nLelkodYBY42+Dr56HwRLa57FIIyzLpcHmKeF4pp8nSFENfWzUOj2RJjtEE5DYWLLr5ksgQ=="
    },
    "me": {
      "id": "917898259805:28@s.whatsapp.net",
      "name": "MINATO ÑAMIKAZE~"
    },
    "signalIdentities": [
      {
        "identifier": {
          "name": "917898259805:28@s.whatsapp.net",
          "deviceId": 0
        },
        "identifierKey": {
          "type": "Buffer",
          "data": "BYxkiNHUj54KHK08gffXO0uOr5soTNuNaKuAyODzl6s2"
        }
      }
    ],
    "platform": "android",
    "lastAccountSyncTimestamp": 1657032126,
    "myAppStateKeyId": "AAAAAJnx"
  },
  "keys": {
    "preKeys": {
      "1": {
        "private": {
          "type": "Buffer",
          "data": "MADJTvBEOtgIREZUEHJjGUUSxyc2wJqvUB5qjAALQHk="
        },
        "public": {
          "type": "Buffer",
          "data": "hbI7NxruCw9UPWdlrSfqp60qzBuL61NNGwbH1jDGQBY="
        }
      },
      "2": {
        "private": {
          "type": "Buffer",
          "data": "oLIewqyVl4PsfSWyWNduRMGGFzd7kn5Zwl7l5hSSX3I="
        },
        "public": {
          "type": "Buffer",
          "data": "rKqYdoay9Fz9ItL42jcyL6d5/qez9A06zTyooZU96Qg="
        }
      },
      "3": null,
      "4": {
        "private": {
          "type": "Buffer",
          "data": "ALBksGiYlJRdCNfeW3gVqSlF7GxizncUWR865XmZd2w="
        },
        "public": {
          "type": "Buffer",
          "data": "hTnVP3mUmU/otu8mX6+dlV62KrzRl2+aNbVOABXJz3I="
        }
      },
      "5": {
        "private": {
          "type": "Buffer",
          "data": "UPjTiusB3+8yb7leSq1jmwDRdlmVQ4/F6PsvydhfuGI="
        },
        "public": {
          "type": "Buffer",
          "data": "BQ4fsl6LMgVONEHr2q5JL19PPN38ktf2cRIDp7jOflM="
        }
      },
      "6": {
        "private": {
          "type": "Buffer",
          "data": "WByl7Z4kn6aDgKtfyChPds/cb2AejrjHHh1ywnisMFw="
        },
        "public": {
          "type": "Buffer",
          "data": "jDz8HJVXCSaafvEvFgkVZDUFI2T/cE/8yaknxk6RSWk="
        }
      },
      "7": {
        "private": {
          "type": "Buffer",
          "data": "sMU++p9u6KcU5S6Pc7ztkk14LCBYcptW2sVvIQXD8HM="
        },
        "public": {
          "type": "Buffer",
          "data": "f38DRU6Ng6d5slzF7Rwlx4wWGpqUYqAeY67fTR4c0m0="
        }
      },
      "8": null,
      "9": null,
      "10": {
        "private": {
          "type": "Buffer",
          "data": "4HFYU/SP+7Z2OtIGhZTMy5A+HMxcj6lBd8b6q4dF3mk="
        },
        "public": {
          "type": "Buffer",
          "data": "mqt5h/VnnHl36PJxICu2TRak10OhcoSAVmGUkphQzF8="
        }
      },
      "11": null,
      "12": {
        "private": {
          "type": "Buffer",
          "data": "CM/fg1vK8SgMPfF1wFVE+3tYPe5pwWp0GK9ZA1tzgk0="
        },
        "public": {
          "type": "Buffer",
          "data": "AyxpjFvoiwH2VdCSnCL1wW/J3KGXiIpUrHJPzZ5NK3U="
        }
      },
      "13": {
        "private": {
          "type": "Buffer",
          "data": "wLSWpejYNdfdKoLY0gYf6hJJtE6V5Ir5pKWZKHkAukQ="
        },
        "public": {
          "type": "Buffer",
          "data": "Md5yd/LzkfH0G+IFBRYLZoKO7dAainvb/AHexJ8odGQ="
        }
      },
      "14": {
        "private": {
          "type": "Buffer",
          "data": "YInq9mgPcJ9IYr4t0nMdsec0GwiEc7y7FTwZiJSJt2I="
        },
        "public": {
          "type": "Buffer",
          "data": "eBbP/2wTHbt/e4Bw/iu2a9byROqEkRwdx9QIRqM6XSE="
        }
      },
      "15": {
        "private": {
          "type": "Buffer",
          "data": "GErn2Ga7p6Ysu8kXA6/ohKAcMpCI7e32YLlgO0qWmWA="
        },
        "public": {
          "type": "Buffer",
          "data": "MvWZO6uc0SUKD/58nCLsv2nSOPqS5Rp/BSn/3PWgEE8="
        }
      },
      "16": {
        "private": {
          "type": "Buffer",
          "data": "eEkOcp2ZXRAmF+3+1kUmtX+AHoVKtkLr2q8QO4a8PVM="
        },
        "public": {
          "type": "Buffer",
          "data": "JI3owZP7XxaXid9tSHascz5iwIpEgCcdpam1d8vXNXg="
        }
      },
      "17": {
        "private": {
          "type": "Buffer",
          "data": "MAq+aae/eC2w3c628qnZ90UOO3bxQSRCq7np3QbDzGM="
        },
        "public": {
          "type": "Buffer",
          "data": "4uaSqXOFL3588zcScEX36kH1FgmbDBmUy4uWJS1x93E="
        }
      },
      "18": {
        "private": {
          "type": "Buffer",
          "data": "2E2EqlqZZTDxBTjLv2pLJuQalMFYFs0bNQGEQITJ5Hs="
        },
        "public": {
          "type": "Buffer",
          "data": "e/rTFWusQQ6jFGcORMVE/MkuNciSd99TSFQDncnlNn0="
        }
      },
      "19": {
        "private": {
          "type": "Buffer",
          "data": "0Mxm+orj9QyTX9HOymbtpYcAetKPMWMDfHtM9TWSrmY="
        },
        "public": {
          "type": "Buffer",
          "data": "u8e+j2kkLkGD4nuiuaP94lEtqxrbpMocjG3yslbmW2E="
        }
      },
      "20": null,
      "21": {
        "private": {
          "type": "Buffer",
          "data": "UHQMsrJDLgHMwXqk1mt8qRLpeUdOsYwN75TTfBQjKUA="
        },
        "public": {
          "type": "Buffer",
          "data": "sB94ay714Bh8QOkO8gKvClaEcj5gG4dAbe70JJH0K3s="
        }
      },
      "22": {
        "private": {
          "type": "Buffer",
          "data": "UFCnmJhS3dp32on4zmF4P/NBOfHLAPib3PjcHi25OV8="
        },
        "public": {
          "type": "Buffer",
          "data": "pu0xVVNl/L8zVto5lleSXmTQCpwwW1k5Su8jH2kV12Y="
        }
      },
      "23": {
        "private": {
          "type": "Buffer",
          "data": "YExtB5k30Fq24NMRnGLd8/P6H9LKBb+GmClEinPN50w="
        },
        "public": {
          "type": "Buffer",
          "data": "OSR7JBg619x6oY06fLf1x91Jj6vQeJC4VIoeY2f9cnU="
        }
      },
      "24": {
        "private": {
          "type": "Buffer",
          "data": "mF9yDpAijRVQAypraCNve4+tpFPyDKzAtqyH3ASw30Q="
        },
        "public": {
          "type": "Buffer",
          "data": "P3h88PfT5zjPG8LtjnLeyLd//T4XaNeNhTaLTnReZGE="
        }
      },
      "25": {
        "private": {
          "type": "Buffer",
          "data": "UHaZzC3P8F1ZscIQZhQ2tBgZEB9at1Yw5OJMikHoQ34="
        },
        "public": {
          "type": "Buffer",
          "data": "/Gj/7hpKzKlgnfOCWsUlp6lLKJF2tmQRjlsNdR2GqgU="
        }
      },
      "26": {
        "private": {
          "type": "Buffer",
          "data": "gOouSBuBzPGlf8dicZAaRjDwDNSOdjJ9yj8HMQMDr1s="
        },
        "public": {
          "type": "Buffer",
          "data": "NLGTMU6qehiwXJFYDbfv0lE26XwcmzmBQ0cW2DRsEV8="
        }
      },
      "27": {
        "private": {
          "type": "Buffer",
          "data": "MI8RExT05BMDV6GRPgW0kyzctm6844zBdqVn5NntZmQ="
        },
        "public": {
          "type": "Buffer",
          "data": "VW5NPN+4kFiImL0jcc9I0aX/1g/GWbeIauWhWpnUCGk="
        }
      },
      "28": {
        "private": {
          "type": "Buffer",
          "data": "0Efh0m4kYbCKIU+UTXr3jVfH9y5iOjrf5dHHT0hlmV0="
        },
        "public": {
          "type": "Buffer",
          "data": "/Vde1bwi5ONRG1/vjAUWSuDnDH1n0G0QnMlZ3omY1Ck="
        }
      },
      "29": {
        "private": {
          "type": "Buffer",
          "data": "QHlGrx4w7DkFZ7lJa/RsW+44XDacgAne5/d9RwRFqmY="
        },
        "public": {
          "type": "Buffer",
          "data": "cyPuFfGE8nlsqsX+oEzu+DC1+GKWDuVSdUzfmck2si0="
        }
      },
      "30": {
        "private": {
          "type": "Buffer",
          "data": "4JxMmXgct6Cg5obapeyQpq6pnWgw4Jl+1aDDD9lbK0k="
        },
        "public": {
          "type": "Buffer",
          "data": "dLgISeoOGY5sm9JmVYk4/AJ657AbnOY8oNAurgnJiwQ="
        }
      }
    },
    "sessions": {
      "917898259805.0": {
        "_sessions": {
          "BYMVwrnm9vtvB6OL+HGqtqzjGVAvQe47wzIeDdy/STgB": {
            "registrationId": 857414588,
            "currentRatchet": {
              "ephemeralKeyPair": {
                "pubKey": "BYeiedHsV+BYOfALuzk/DrndFehLX0LG9nNSt55qXPc4",
                "privKey": "eC7M/OtmBKzGAcoP+AK3tk1HnBHFNeG7zm3guEuNyl0="
              },
              "lastRemoteEphemeralKey": "BcHTbuAQVFlVuZNI8nquFEPz4rHLvoTuSpi1WZC3qDIS",
              "previousCounter": 0,
              "rootKey": "299rGLD1jUg2cdfgCGC1kl4ozOECq1sZY4p2+qum6BY="
            },
            "indexInfo": {
              "baseKey": "BYMVwrnm9vtvB6OL+HGqtqzjGVAvQe47wzIeDdy/STgB",
              "baseKeyType": 2,
              "closed": -1,
              "used": 1657032127415,
              "created": 1657032127415,
              "remoteIdentityKey": "BYxkiNHUj54KHK08gffXO0uOr5soTNuNaKuAyODzl6s2"
            },
            "_chains": {
              "BcHTbuAQVFlVuZNI8nquFEPz4rHLvoTuSpi1WZC3qDIS": {
                "chainKey": {
                  "counter": 4,
                  "key": "BtnGzOJBPLFKmwyzEL9HQBGsIxPp45VeAr3NgfyqM4w="
                },
                "chainType": 2,
                "messageKeys": {}
              },
              "BYeiedHsV+BYOfALuzk/DrndFehLX0LG9nNSt55qXPc4": {
                "chainKey": {
                  "counter": 1,
                  "key": "dumRnhOQ4NDzfu/Miroq2s4DRKnKqFIWdIfXJbf/hlE="
                },
                "chainType": 1,
                "messageKeys": {}
              }
            }
          }
        },
        "version": "v1"
      },
      "919003198861.0": {
        "_sessions": {
          "BQrWfSRhs6MuKahmvPtb2KVHGKr6dmKTmepGi51tnCUJ": {
            "registrationId": 850387516,
            "currentRatchet": {
              "ephemeralKeyPair": {
                "pubKey": "BWtKxcbkGp45XDn8hN+SvEoisRVAB8flyBF55WCDhpci",
                "privKey": "iKoiGp78DBFMq5gzZNP34kTNbUWWxf3a0RAEpJRIjXM="
              },
              "lastRemoteEphemeralKey": "BQj/v7PGFvI5uSI6dHZgPw7wDenaVdmG799Hb6uSAS8i",
              "previousCounter": 0,
              "rootKey": "fAXgacLOHH/JGPDE2YjdaDZakJY/AAZjzOcPTYic/c8="
            },
            "indexInfo": {
              "baseKey": "BQrWfSRhs6MuKahmvPtb2KVHGKr6dmKTmepGi51tnCUJ",
              "baseKeyType": 2,
              "closed": -1,
              "used": 1657032131191,
              "created": 1657032131191,
              "remoteIdentityKey": "BZsM7m4wkufxf9Np/v4yGZBitLaspFsth3PeJN8exdwz"
            },
            "_chains": {
              "BQj/v7PGFvI5uSI6dHZgPw7wDenaVdmG799Hb6uSAS8i": {
                "chainKey": {
                  "counter": 0,
                  "key": "3LMYdOImrjWaFJBNWC7gmal8lC6Nj6zKOZvVZfYnxqg="
                },
                "chainType": 2,
                "messageKeys": {}
              },
              "BWtKxcbkGp45XDn8hN+SvEoisRVAB8flyBF55WCDhpci": {
                "chainKey": {
                  "counter": -1,
                  "key": "cTpOcbWa0ZmFQMwEsaJDP5lRbbeEBq9b+iLL6YhycqU="
                },
                "chainType": 1,
                "messageKeys": {}
              }
            }
          }
        },
        "version": "v1"
      },
      "919305472884.0": {
        "_sessions": {
          "BbrE5r+mLIHudlDBtPEfM6+9+r23gT0lu07C3rQKRRAl": {
            "registrationId": 2016666248,
            "currentRatchet": {
              "ephemeralKeyPair": {
                "pubKey": "BXLyhSw/wEl9cuQk3auKM/p4VZ+VsNMav4+ZNwbEgS5b",
                "privKey": "WEppeyzUxWQeAWe7Uw2n7Sov8sEA8EpFdBWNLNasoVc="
              },
              "lastRemoteEphemeralKey": "BePhsPrEW8/uXRh8/181ONZ83e+yBc9iX5DVdHf7fKw7",
              "previousCounter": 0,
              "rootKey": "L8VlktjJNi3vsbijzE+k52CmrtgX9sXCO7CsVgaWHHE="
            },
            "indexInfo": {
              "baseKey": "BbrE5r+mLIHudlDBtPEfM6+9+r23gT0lu07C3rQKRRAl",
              "baseKeyType": 2,
              "closed": -1,
              "used": 1657032133641,
              "created": 1657032133641,
              "remoteIdentityKey": "BYMnWKwM64iT30U0hceXLTYdrgh+SegQLCy1AMY4RPls"
            },
            "_chains": {
              "BePhsPrEW8/uXRh8/181ONZ83e+yBc9iX5DVdHf7fKw7": {
                "chainKey": {
                  "counter": 0,
                  "key": "utFYgJleRM7/67ahHZ8DUa6pV93cs449vGGr5ivYI+U="
                },
                "chainType": 2,
                "messageKeys": {}
              },
              "BXLyhSw/wEl9cuQk3auKM/p4VZ+VsNMav4+ZNwbEgS5b": {
                "chainKey": {
                  "counter": -1,
                  "key": "GHXUbza/vegzaTkkXKz2w6ZwWx/q4pkKM1MpafPVpyM="
                },
                "chainType": 1,
                "messageKeys": {}
              }
            }
          }
        },
        "version": "v1"
      },
      "918149991773.0": {
        "_sessions": {
          "BeMDE0XrX5Td+fK1J+tN0WlP1TTz3tCtCV1wDqinMO59": {
            "registrationId": 1547245894,
            "currentRatchet": {
              "ephemeralKeyPair": {
                "pubKey": "Bdhw1f14erDsNV+ngdnARrOSU++dSyh5p/YwlVeW4qQu",
                "privKey": "yMN9hrptVvhjzACf+mdshEOFUxX8R80fx50XvmQ2iHo="
              },
              "lastRemoteEphemeralKey": "BTzhZo42DESQWGbZ6QJdCOcRlQbKLy/nYiqh6E7+TrBF",
              "previousCounter": 0,
              "rootKey": "6VPZzUKnCnria3Rv3OzTDy0ILbfV6xwAbiyK6TJYosI="
            },
            "indexInfo": {
              "baseKey": "BeMDE0XrX5Td+fK1J+tN0WlP1TTz3tCtCV1wDqinMO59",
              "baseKeyType": 2,
              "closed": -1,
              "used": 1657032134673,
              "created": 1657032134673,
              "remoteIdentityKey": "BTFaHE6a49xMxvYLeuC3ou52lIe+uxULVOu573y1/0g5"
            },
            "_chains": {
              "BTzhZo42DESQWGbZ6QJdCOcRlQbKLy/nYiqh6E7+TrBF": {
                "chainKey": {
                  "counter": 0,
                  "key": "SoU7yjER7IIHzLqGILZu+Us+eSC+S7XL0E+wYSxquvg="
                },
                "chainType": 2,
                "messageKeys": {}
              },
              "Bdhw1f14erDsNV+ngdnARrOSU++dSyh5p/YwlVeW4qQu": {
                "chainKey": {
                  "counter": -1,
                  "key": "k72N41lm+34moPscfCf+MMfLdapKGsV729Kce+2Vfpg="
                },
                "chainType": 1,
                "messageKeys": {}
              }
            }
          }
        },
        "version": "v1"
      },
      "918446298623.0": {
        "_sessions": {
          "BSPfTILgTkt0Gdr6KEGoTTKUkhzg+rxAKzjf3OXshsZQ": {
            "registrationId": 1459318192,
            "currentRatchet": {
              "ephemeralKeyPair": {
                "pubKey": "BXpQLaOxXnUoqN+bH2lmCNIT9KYZS0hbLOKhEOA97kdL",
                "privKey": "wCL9YSAl8JPg0MIZAwkqB28wdFZqgzeGuK4CmYea50w="
              },
              "lastRemoteEphemeralKey": "BXIQnmOBg6S2hEZSSUYZUWZPjcbzx9UbZdxXeNBJDu5A",
              "previousCounter": 0,
              "rootKey": "T4hj+zwCAu0o8VWqsc7asQ8MNkKmlOP6YIany63lZqQ="
            },
            "indexInfo": {
              "baseKey": "BSPfTILgTkt0Gdr6KEGoTTKUkhzg+rxAKzjf3OXshsZQ",
              "baseKeyType": 2,
              "closed": -1,
              "used": 1657032135217,
              "created": 1657032135217,
              "remoteIdentityKey": "BeLM1d1F97E3U5YsrSPgVAxjKuMU7l/1KNjQAGnJqSFg"
            },
            "_chains": {
              "BXIQnmOBg6S2hEZSSUYZUWZPjcbzx9UbZdxXeNBJDu5A": {
                "chainKey": {
                  "counter": 0,
                  "key": "xdqX4uUneInCiSTTO/SVOcCWgsA/noC6tN5YAPaAGJA="
                },
                "chainType": 2,
                "messageKeys": {}
              },
              "BXpQLaOxXnUoqN+bH2lmCNIT9KYZS0hbLOKhEOA97kdL": {
                "chainKey": {
                  "counter": -1,
                  "key": "fBVW1XFCOXZDC+L1UX4rSfhD/QSagsObGCf7U9cQXfA="
                },
                "chainType": 1,
                "messageKeys": {}
              }
            }
          }
        },
        "version": "v1"
      }
    },
    "appStateSyncKeys": {
      "AAAAAJnm": {
        "keyData": "m3vJtVxoCT9jG/uQ7Y9IqbcofagL9gS6o8bLZqiPCag=",
        "fingerprint": {
          "rawId": 1445972906,
          "currentIndex": 1,
          "deviceIndexes": [
            0,
            1
          ]
        },
        "timestamp": "1655921828774"
      },
      "AAAAAJnn": {
        "keyData": "E+lPwTVr6wjg3pj3JgOiPAhPoIXb+NZprQUSrWGrh7s=",
        "fingerprint": {
          "rawId": 1445972907,
          "currentIndex": 1,
          "deviceIndexes": [
            0,
            1
          ]
        },
        "timestamp": "1655923269447"
      },
      "AAAAAJnl": {
        "keyData": "dnoGNHhUcQjQa6l5LTaOWIoxfBhU2pVw30SpPoaJ8ws=",
        "fingerprint": {
          "rawId": 1445972905,
          "currentIndex": 1,
          "deviceIndexes": [
            0,
            1
          ]
        },
        "timestamp": "0"
      },
      "AAAAAJnu": {
        "keyData": "eVJmWbNGCrdWFS6+D/QrFU0HoADcHaWx65yc4qTS1M4=",
        "fingerprint": {
          "rawId": 1445972921,
          "currentIndex": 1,
          "deviceIndexes": [
            0,
            1
          ]
        },
        "timestamp": "0"
      },
      "AAAAAJnv": {
        "keyData": "KEomalYeQ3w8rrdj1xfoxjJ9VpE1WlPkfjV9jjk0pRY=",
        "fingerprint": {
          "rawId": 1445972922,
          "currentIndex": 1,
          "deviceIndexes": [
            0,
            1
          ]
        },
        "timestamp": "1656438986167"
      },
      "AAAAAJns": {
        "keyData": "eBQwGSewoH1eQU0p8DkGMBLt6N2p/lJkTW2/1x1DZ1E=",
        "fingerprint": {
          "rawId": 1445972917,
          "currentIndex": 1,
          "deviceIndexes": [
            0,
            1
          ]
        },
        "timestamp": "0"
      },
      "AAAAAJnt": {
        "keyData": "1aS7VD7+CUkeI5I0GxWdsmwQa55npk9FFEuYZaifsRY=",
        "fingerprint": {
          "rawId": 1445972919,
          "currentIndex": 1,
          "deviceIndexes": [
            0,
            1
          ]
        },
        "timestamp": "0"
      },
      "AAAAAJnq": {
        "keyData": "meDCIDQHCZRUR/vnFkFgsrwz5vzG/NsRs8Pa7MdPk6E=",
        "fingerprint": {
          "rawId": 1445972913,
          "currentIndex": 1,
          "deviceIndexes": [
            0,
            1
          ]
        },
        "timestamp": "0"
      },
      "AAAAAJnr": {
        "keyData": "+prs8lk5DhhR8G49nNfUvbdUXb8zijRlvrS0DqbwwWY=",
        "fingerprint": {
          "rawId": 1445972915,
          "currentIndex": 1,
          "deviceIndexes": [
            0,
            1
          ]
        },
        "timestamp": "0"
      },
      "AAAAAJno": {
        "keyData": "4cAlxMPcBNobUlcoP7oclDs37JRdvDIAlFKaAqJ/mI8=",
        "fingerprint": {
          "rawId": 1445972908,
          "currentIndex": 1,
          "deviceIndexes": [
            0,
            1
          ]
        },
        "timestamp": "1655926189499"
      },
      "AAAAAJnp": {
        "keyData": "fWtAxHu2UC8ARFEFuzO0CyTdOyu/k57nGI7/05SfKi8=",
        "fingerprint": {
          "rawId": 1445972909,
          "currentIndex": 1,
          "deviceIndexes": [
            0,
            1
          ]
        },
        "timestamp": "0"
      },
      "AAAAAJny": {
        "keyData": "ng6IvsIZaFUlk+qZDCXRTYF0CGphbwQlIrRDW0U/JOg=",
        "fingerprint": {
          "rawId": 1445972925,
          "currentIndex": 1,
          "deviceIndexes": [
            0,
            1
          ]
        },
        "timestamp": "0"
      },
      "AAAAAJnw": {
        "keyData": "JiMG7IwxopAzNg4+fHrZmleCC/5FvZE6/SC7wyFYuzs=",
        "fingerprint": {
          "rawId": 1445972923,
          "currentIndex": 1,
          "deviceIndexes": [
            0,
            1
          ]
        },
        "timestamp": "1656439018853"
      },
      "AAAAAJnx": {
        "keyData": "HXFhO4Vy7SNl/gVsN3dGiMjEkz4YeKuyUiOxKA1zw5I=",
        "fingerprint": {
          "rawId": 1445972924,
          "currentIndex": 1,
          "deviceIndexes": [
            0,
            1
          ]
        },
        "timestamp": "0"
      }
    },
    "senderKeys": {
      "917695881551-1625391376@g.us::919305472884::0": [
        {
          "senderKeyId": 802340322,
          "senderChainKey": {
            "iteration": 96,
            "seed": "ETo4BKnMhj7bSHkQNMEt9P6eq1swKzhqBjrAGo9DT8U="
          },
          "senderSigningKey": {
            "public": "BfEqdj5n3hezlf5rE6U46yfcjkP98PJSzm0RQ6HxTSFj"
          }
        }
      ],
      "120363023668089059@g.us::918149991773::0": [
        {
          "senderKeyId": 970091448,
          "senderChainKey": {
            "iteration": 1,
            "seed": "BFH0nNJwcBw/lwp6zG6hphEXC9CcNt0Fn9mq4SirieE="
          },
          "senderSigningKey": {
            "public": "BRwI1L/q7zfLWn16MbIh1D9w6SGaQYs8DGtMN4LOGqBK"
          }
        }
      ],
      "120363045885303443@g.us::918446298623::0": [
        {
          "senderKeyId": 1212602189,
          "senderChainKey": {
            "iteration": 167,
            "seed": "tMjl549bX8+PH9c7dagik/uI8Evy//WIwFOUiI0fOxA="
          },
          "senderSigningKey": {
            "public": "BS3jHjyjmxDGaON1rF8+umvmkqG+odVxCDcFiMNOYnld"
          }
        }
      ]
    },
    "appStateVersions": {
      "regular_high": {
        "version": 56,
        "hash": {
          "type": "Buffer",
          "data": "iEMtX71v+ZGz85FpdbIpBHc/MhTp/8gOXXDAsgvvHfFJFKNqwtQyT/EQlqfWn/RdhC5Hl6vOAnP58nwhI8ZeXyvqt26E45ccyY9icq8Olh5NF0lNUKu/UJdkXfqxORIJDTsqZ5CT4tqv2Sie2x9Vt6JCfHzHlKuTKUdHw8xHqyM="
        },
        "indexValueMap": {
          "AC6IJucefD/t/uXTyra/Ndv7tCw3OMZypGCy0qbawP0=": {
            "valueMac": {
              "type": "Buffer",
              "data": "y1iZz+BjR7ECfA5k+QqRJS6Ir6ypG6CJpxHwoAKIxiI="
            }
          },
          "AftrXrN90FtI759f2FbDiwmtTHo9OCyG0ZMzDKNRVa4=": {
            "valueMac": {
              "type": "Buffer",
              "data": "amIeHYcIKtf2upZCBQUC+zLAvzZKRPW8Za3yM+1Hfr8="
            }
          },
          "BFZ0oDRfBESsV4YTzdtsc18WeuTbzhcEPPWQTxh7wEw=": {
            "valueMac": {
              "type": "Buffer",
              "data": "TDom10TLF+hMhEOT4gGLpdqxV9SGrwF+P97wkUzXX1k="
            }
          },
          "BGDyGdPjbEi/++8kZCMhcRVFahvO/wH9XfEhgywldmI=": {
            "valueMac": {
              "type": "Buffer",
              "data": "2nSoWAw8Pu1hWG0muW/OdfDLzlFzbsOyEHuRvYcivT0="
            }
          },
          "BhXsB42eCg7cUnKRdQXjtoYWsTQno8tocopEwXwblAQ=": {
            "valueMac": {
              "type": "Buffer",
              "data": "Zr0x3RZctDM4ngEPMIxz0AY1Dd3RBU3Yw/MQcCt0IwU="
            }
          },
          "Bo3/ud7qStb+VfVwxHrLFtmkX6bbKcBtgfL3cAd0/m0=": {
            "valueMac": {
              "type": "Buffer",
              "data": "mek15YmrsGfBjXwPtzyA4I1WpXK2+35/MzHGKXa4+rw="
            }
          },
          "CQmjK9D0pPVVokCkHXLMgxHsBNbjnbGBOXb+Ped6USc=": {
            "valueMac": {
              "type": "Buffer",
              "data": "+IrZdt/9nFTUQbJdr1UIuPsJQLEjZ1XcygwQr8VlRUo="
            }
          },
          "CZn5PY+lW+25M/jBnQsNMjbQq8nepfF7LR3tHw24oVg=": {
            "valueMac": {
              "type": "Buffer",
              "data": "il/qLEt84/ZxENlNguG0D4y4UbYaNorUlrqpZ6wSvAA="
            }
          },
          "CgOxBdmcC2hB4jFDfpLELEQHsnXq0E/wt+J4WJ6kQQY=": {
            "valueMac": {
              "type": "Buffer",
              "data": "GEucNTseYxB80iyPBbT2BaWvsgpxm9zq6M/L3oJM9Mg="
            }
          },
          "CqgJnThgipv+Zx3+vmSZ8UEldWSBqBL/qAHyfveomug=": {
            "valueMac": {
              "type": "Buffer",
              "data": "iRx4pY5AWhuZEhdut7b5oiy8d8NgDxpK1JGWFuUS4JA="
            }
          },
          "C2l7NwPyJAuCkGFe2qmIW0ipdIPOIKDbkvitj9NG3Lk=": {
            "valueMac": {
              "type": "Buffer",
              "data": "ydlsqCCXTf7Y/1VsNlwsjEKab+tZ1AwyHXChrA7EfbA="
            }
          },
          "C8VTnVEOySgl+oQ8llqhOu9IaVvfSClYYogCbP012fw=": {
            "valueMac": {
              "type": "Buffer",
              "data": "FnoldUSkqRXHv1kxayIJpCgBZPwD4wsv8AzjXAbup7c="
            }
          },
          "DeMgbm2zbF+FYwn3x+wDyj9AWP5Ltq/h57mMJx06tEg=": {
            "valueMac": {
              "type": "Buffer",
              "data": "7qMn5ZhpV5OvB3pkU/U9AdK6dpRzvFbN+Ila7VSKfVs="
            }
          },
          "D8JLKSpaKM/DjsMvcpVvD7u87d9grKhZSxmnxJ7GpTY=": {
            "valueMac": {
              "type": "Buffer",
              "data": "rGZI0Gm5SFYyBSCkaqjrB9lbKuoN68WWvIHwQUu70qo="
            }
          },
          "EKyjQXvIhxHnCUTrkYIbRj2wDTJZ0gNdRWbVFoUXOIw=": {
            "valueMac": {
              "type": "Buffer",
              "data": "yOOy3eVHhGwGSJJ6Hu3v3F+13m2O0lSfd2aplnkVpfA="
            }
          },
          "EPS7RSRTzwvUaoBzdfryyv/25bxOywwnsx+WSVziEMQ=": {
            "valueMac": {
              "type": "Buffer",
              "data": "C7pgNvaxX6g7WMjsvJ4PNxHMS95NgMlTXaeMIHHUAvU="
            }
          },
          "EpcVUmV2IHNAVG67itrs1VizDMYDCdWPpVA97NZqW/o=": {
            "valueMac": {
              "type": "Buffer",
              "data": "rbxLSuwmSlNTWOb+YtLJWkgAdavOSQu0tnw4S4gsivc="
            }
          },
          "FRt4arTYMbpfYszYinBr8HAIHbmmoIO5sG/Vl7xpN/w=": {
            "valueMac": {
              "type": "Buffer",
              "data": "sl2PftzutIIvtijzpagWGrA49aYbI9nvPdtbelkOsIU="
            }
          },
          "Fjv/bfmVt0T2yxRicUTkJ9VxR3uY0i0hWME68geCQlI=": {
            "valueMac": {
              "type": "Buffer",
              "data": "vyd1JbT2VZh8GI27Awj1wOm7O863LemtnIe67nRBS/M="
            }
          },
          "GFgY80915oaH9IQQTF/MAVOoUMzk+owMFFG2lkshlkw=": {
            "valueMac": {
              "type": "Buffer",
              "data": "7KqumgG7ArJvOTGQSNgew0EhENBpmMmSTpUBeoPotVU="
            }
          },
          "GTB8wbPLy4s5OntuAa5qcq3drw6gwJL+lIb66Q77u8M=": {
            "valueMac": {
              "type": "Buffer",
              "data": "ErhoFrCT0QU4Iyj+g+600icUU2aL+HH0XtX8xcTN8yM="
            }
          },
          "Gn1perMRHHgl8a0ojXMdKWaZ/KzRYL2ZV5hIT388hLc=": {
            "valueMac": {
              "type": "Buffer",
              "data": "GJldSZkRRPVD7R5B76aMsgUxBAB1e1oZKNXAn8NCHI4="
            }
          },
          "GvBnNs+zS0FBNNfkHx8dlRFGyFOAxHwLZveGszII5D0=": {
            "valueMac": {
              "type": "Buffer",
              "data": "sfi/zGU+E9lZmTkdlX56YOL4ig/N8atMNlcTV+8Fx5Y="
            }
          },
          "GyaCG0IvSM2I15D8u5rli6FT18Lj5DIS9OjDde6YvOs=": {
            "valueMac": {
              "type": "Buffer",
              "data": "p2TThk+XnAphFAXun0cMWpvGEifmRrdET5VsSRj7Egc="
            }
          },
          "G6XTMQ90+9b9CT0SFPNv5Q9It6xVs8vyC+MKc/F+ldM=": {
            "valueMac": {
              "type": "Buffer",
              "data": "4qzvH5CQXQyqG+NYRHi6v0LhGYKno4g5t2udHoWIm3o="
            }
          },
          "G99EJ4mHiBpDe8PwiIKxtnfwy8I8DjEFvkmlxzAtmzc=": {
            "valueMac": {
              "type": "Buffer",
              "data": "uBDcRHUzpEraVHIY5WiAUsve+7qztdyczAfc7UxSV8A="
            }
          },
          "HH6enkjXfcO9RkQ8o6r1FcA+gZmz2N5br68vd+QStdU=": {
            "valueMac": {
              "type": "Buffer",
              "data": "Mcz8avOpaeYsRcEhNBpq6qiIy1uuG9Yc4/rMQ38JLs4="
            }
          },
          "HLdoHLmeH9fuiplaJNiyL4ZdQYHsg9DLZuwKUEGnNr0=": {
            "valueMac": {
              "type": "Buffer",
              "data": "y/ba/WfJQjFx7YfEWLjKkt1dSkI/AlpM3AlQMzvDnzg="
            }
          },
          "HSfoJ0d/2FO9MI18ztr8NF+toCFyyqxp6kFxhSsC6KI=": {
            "valueMac": {
              "type": "Buffer",
              "data": "8xBT1bjoBDpMFCx4Fccy+Xyt16+Bhu+b9YlXW6mdklI="
            }
          },
          "HXdd+6MfUBMU04XmbzoydLGKFIxJVjGzxyfvEcEiIPU=": {
            "valueMac": {
              "type": "Buffer",
              "data": "8sv4w8Vn+2vR5456rdKduCkkB+gAneCWIX6XyORO5Lg="
            }
          },
          "HZjcErRa0mQVCN6xwoBmPIwDl86t+ecAnqm1pgXyzQE=": {
            "valueMac": {
              "type": "Buffer",
              "data": "B9UzAmBmDhgn8XxkPLLqo2UtU1QLxkeJwI66a4q4r2A="
            }
          },
          "Ht9gcmf4EGhRk9tSrr4g4JOzEYjY2PzFcvbEJh1PV1w=": {
            "valueMac": {
              "type": "Buffer",
              "data": "E8pYWptoSYI+TJqYxqpxnqh2RanRNiAPrbKgOwlMnfM="
            }
          },
          "HxKputGks6gXdeggYVNJTf8x0CbuxqdXrmomB8gFrYk=": {
            "valueMac": {
              "type": "Buffer",
              "data": "AW4pQUAf5jdBwUsCTLOzunOCDMazXucvXsx3UjQtlnU="
            }
          },
          "H81zQAJBWF1j4xMQgsfPaiUqs2ds8Po/x54FgD4ty9E=": {
            "valueMac": {
              "type": "Buffer",
              "data": "LRnxUcQe2+mIFmfRXdoerMo4wjmf6LR94wiKi5Zgmj8="
            }
          },
          "IPnYSwt1/3x4ezVXgY/EK5duNGdD5FJ7hDIUzFxpd/U=": {
            "valueMac": {
              "type": "Buffer",
              "data": "D1OFw3/l4I+N0D4YiNbRzWuieoMYKeMeKAWR+u0/DDs="
            }
          },
          "ISCN8HnBUQBCtHbrFsIMSEK/wuupF651A+Ztj+ahQCM=": {
            "valueMac": {
              "type": "Buffer",
              "data": "FXWGo4SMBoPE7AphyfC6Cdp9i4SEV06fWJrP3Eq7olI="
            }
          },
          "IUBhPiva148XbMWqs8rQvKFU79zkCwb58TpkCrxB1sQ=": {
            "valueMac": {
              "type": "Buffer",
              "data": "4dundO5oXSHQu8ZoBrjKcTJX9ItoHqw9WzWLOwRwKQc="
            }
          },
          "IUL1Y1t79fDs5FV8mesFfsBmRkOxeVrLwZ7Fg9LeUvc=": {
            "valueMac": {
              "type": "Buffer",
              "data": "ZJ/x8QPqzHEm5tD4U5IUlEIVfySqYiLGyckPeRJHqOo="
            }
          },
          "IyZ91FQgShdlxSSYHNS746FuTSUfZTjndnqqeEZQjO4=": {
            "valueMac": {
              "type": "Buffer",
              "data": "nrDB/Li/TuIkRz0Z1QmhXsH2a8f6ADWE73JGmLQ4qug="
            }
          },
          "JJsSpYWm+eH4wzjf6h5M0RTE9JvGzmGnBuZ9Ukgoom8=": {
            "valueMac": {
              "type": "Buffer",
              "data": "JxVQRJ7OIL5VErVa/i+Ay/8bTf4zqd0XcdPz4a8LIeg="
            }
          },
          "JU+wcqdg0G/DbCV34UMBomghiEGyfgKSCI0sSnwPn4c=": {
            "valueMac": {
              "type": "Buffer",
              "data": "fvMrHrGUEdyDhrVcRZy5/pSVd96ib5JA3MjCV1zSLNI="
            }
          },
          "JZAw2UUcfm8kYOpyOKkFM/bDVGjzUZtvkWxYbNGQXYk=": {
            "valueMac": {
              "type": "Buffer",
              "data": "8N+swHHLyhcKTYJcFmjbw3+9KHTjZEc6d+97R+YeGdM="
            }
          },
          "JdyKe+U8PSM2d6bpHvqdvlqIme+aeIGlflIkq+il3Ls=": {
            "valueMac": {
              "type": "Buffer",
              "data": "KB4qfqsQ3bIWsXSu98igNAYk8mILBBZty615q/1AxMc="
            }
          },
          "Jyq9axuZzDpRaQHix4hTNPwXAMKCOpoi+/0Ra1e7oLY=": {
            "valueMac": {
              "type": "Buffer",
              "data": "j8KFE9OIt4dFS1ozDX6eLoj8i5/no6pgzBCtjomZfmY="
            }
          },
          "KH7fef9NgQKzqFQuK2rI2oHnPQVblUEmfsUcMqle1YY=": {
            "valueMac": {
              "type": "Buffer",
              "data": "qtOsjEYZ1UQs7i0xzSTd6SIII5pias9Wyi+ZEye/kKQ="
            }
          },
          "KyaEGNhSnLYpDzoYA/jlDKlH2spdyOrwkEAkC3be914=": {
            "valueMac": {
              "type": "Buffer",
              "data": "Lh5Sq72aBsL8X8rbR41oiQqZFLZ65slIQrpPrq05Vhg="
            }
          },
          "K/E1CJR1EqgM7EZHYG+GZb9t/ny6oxMkg4hUv6t+4Hw=": {
            "valueMac": {
              "type": "Buffer",
              "data": "65Qu23cBj5QXFdtfAQK1UD9p9od/w6nur+8rFy4qmeM="
            }
          },
          "LN8iw846hylPjnFFuL+UKMXOilwcQz+Xf1BpBxRJbno=": {
            "valueMac": {
              "type": "Buffer",
              "data": "f9tCUvHq9e91XkSxp7EgCHtLN9BFdx+lR9HVhDe9gAU="
            }
          },
          "LOxM+qyqYrOaJRzQynjGXhPndREE/povFzm+kTpz2Ig=": {
            "valueMac": {
              "type": "Buffer",
              "data": "QQdRDw7XyTtvGb4GaLHgkmQTKZzff3Mz89UkzEcMOBM="
            }
          },
          "LQrYAMq9ViO2TxqKz9m1fGmnzYsnECxC3KtTInfpsic=": {
            "valueMac": {
              "type": "Buffer",
              "data": "R3DlGdyH8AoJocE5MGw6bO/58MouNJJ8XKFt5hQdWZ8="
            }
          },
          "LVazTPDrFl8IbjkYneST/Z4Y3bl6aq9Va8WgBa+ZF9Q=": {
            "valueMac": {
              "type": "Buffer",
              "data": "BXHdrbkUiTiT50dLVdUbmxNJwAO0LUciRmmEez7oql4="
            }
          },
          "MOatdjpFi5dEKzdgosuXIGjJcxxSl5tYNA1w07JhAFc=": {
            "valueMac": {
              "type": "Buffer",
              "data": "TOcVjQsMSSwOyABRJql2hHQgBsh20uQ5RBl6F7mXpzU="
            }
          },
          "NE+w1DDtf2PwT0/3SUY27dE98UKL3f1G5vv3F/ztCyg=": {
            "valueMac": {
              "type": "Buffer",
              "data": "5UVIFpxJIjCTwkKneuOrhdOE33kSDJsOA5M/q95VGh4="
            }
          },
          "NZ9gW5eivK7TDeSUFnQfI288tjO7YQY/iLPyaFUY9gM=": {
            "valueMac": {
              "type": "Buffer",
              "data": "7RLtPB2dKD9cnOELxBTydQZBoT5lEOFbqfbmAf0bmKM="
            }
          },
          "NnZHMsx7S77YCcxau9XIMdul9a19bANGt4SnGhcW3DI=": {
            "valueMac": {
              "type": "Buffer",
              "data": "KaJPaWO26hwQiqbzzWlTy1KQly57mwRVH4fJBQLiz8E="
            }
          },
          "N53huD8IVZ4jCkNThLbEF1x4SDa4OoYQa30/ejMnHV0=": {
            "valueMac": {
              "type": "Buffer",
              "data": "/0wrxGjeIJrLgxGBnDc9uLZ/svKSBv8nVNAecBDZf4A="
            }
          },
          "OKKRYBj6OOX46SGY98Wv6q9zbfCvibLoieMOxaeB1NY=": {
            "valueMac": {
              "type": "Buffer",
              "data": "IOJREW6UaQILOFubtOGGtgNipj63KFXNNxdNpFKO2gQ="
            }
          },
          "PazW5LNxDj8EJe4aN+n1mFmUnKuwa48yohBCf/x2YtI=": {
            "valueMac": {
              "type": "Buffer",
              "data": "9CjgqgKlSltHRtE/1iX+pEYIk39WK5uUqdbuNJFChwM="
            }
          },
          "Pe5IEwsyyt7VSgCciQQm8+ws86544rNSAfzIyq48WO8=": {
            "valueMac": {
              "type": "Buffer",
              "data": "hQmyrlzTv9A/abFGv2xzDOzu1hVqRUX3ldaLQbIICfU="
            }
          },
          "QarRzO5pyi0Z1fjeUR06bnKDiwwcJUS5tr9bJo/DQRc=": {
            "valueMac": {
              "type": "Buffer",
              "data": "bQdpgaAmjlIES7vSZdn7T2f25hR8i6ghtBsYHslI4E0="
            }
          },
          "QwUbEVM4g4rx04Vgr5KPG5msnFgdGrVBSNo12E06NmA=": {
            "valueMac": {
              "type": "Buffer",
              "data": "zghPfjUyfllrXK97xwmQLRfYgaGE05q8b1LppUdTRP8="
            }
          },
          "RAGc/4kAhILDph+IZm/vTdWI/N4AXX68/gl0NdE/mfc=": {
            "valueMac": {
              "type": "Buffer",
              "data": "EgrvYINz0WDZkFreTBCpcIGWlaAbdq2wh+ioYFvRRI4="
            }
          },
          "RsRIweh+7C+YCSi+b9DeIE5+gr58gTMcQvC8kjyn5BU=": {
            "valueMac": {
              "type": "Buffer",
              "data": "Ga+58+SbMCq8Nt4ttGfi0bTWkGWs5UIQGCF/WZWd2m4="
            }
          },
          "RxY1Gw4MT09QmNkOjeKaOn06RRVk2r05Wd4bd8LpBy0=": {
            "valueMac": {
              "type": "Buffer",
              "data": "IwGCp4LPppbXRjbysmpojnDYVezY6ay1005kukjkAzA="
            }
          },
          "R0frmV2uFe4n3rYeyCSsjXAToGXLJk+zSlInOw6yaro=": {
            "valueMac": {
              "type": "Buffer",
              "data": "xDaOxgm3Y4u0WDb4XOT0yqKecv0y7rfIHJdsXEOnmnw="
            }
          },
          "SaXJm2PX7LtpqOwAMc+Exm+K1AsFPuf2ZQgKDM4/OU8=": {
            "valueMac": {
              "type": "Buffer",
              "data": "TzLTokyY0SIPxavFGh9ItWmDu/Ci+m5DHGJu1hO8Yh4="
            }
          },
          "SeNodlRzksIkuZe0TYqfM7zS9gS1W65O/ZMOtlqGxoE=": {
            "valueMac": {
              "type": "Buffer",
              "data": "16cQrRI0u086f+TKYrPsNT8+olA3re3WtXk3+ZZKhq4="
            }
          },
          "Ssq6m5Fz5KAYDhlRD5uxWI6kyVq+stnT/a6HYbQcaXQ=": {
            "valueMac": {
              "type": "Buffer",
              "data": "o9MBIzZnTSpkEze0JC8ok3d20CWZL58ToN5pMNq9obk="
            }
          },
          "TDj2Bvfzo6TatoUe8PsGwkOPjEjRziqsxrS7m+lSS+c=": {
            "valueMac": {
              "type": "Buffer",
              "data": "sewmhMv0Ov76pWgIZwAoDcMTfQuy6pplrpvbK+gDbY0="
            }
          },
          "TieAHGq/J3eJCuYO8kl/Jx+e7PZACSdUJqhZvvjpq1Y=": {
            "valueMac": {
              "type": "Buffer",
              "data": "zmiW1TE2RyQnEJnC9bNmM/UPMYd4OEJBtdX9AAjQMbI="
            }
          },
          "To2drbC16qfUxbnbE3AriI7Mjsfv+pHO8K1JCAlxgNo=": {
            "valueMac": {
              "type": "Buffer",
              "data": "MnP5UwjZCL6nJ9/hanFGwk9qiQeEzrvOG/OMb2LYGWk="
            }
          },
          "T7ZCWYnO3zu2rMj8Zv/flnukFW5K7wzkNMnOxJSklCE=": {
            "valueMac": {
              "type": "Buffer",
              "data": "CCaIiHr/tppL+EEEoJNOApynA7ZCKLF+L165KkN0TDg="
            }
          },
          "Uf8mI5PI5GhajGiEBk7HXmBfvUTZQwPSe7vAJa8Q4SY=": {
            "valueMac": {
              "type": "Buffer",
              "data": "swi27AVyuOddCDbcizBT2HeyHm2htFMgxpFemvsmoLc="
            }
          },
          "UjlUPjda6lsSim8QNDVztXDUEz5vdSbV9zk9LV9OAlM=": {
            "valueMac": {
              "type": "Buffer",
              "data": "XD4HW2bN53HgEkXtmkHCWCwdLMk5aCWKAQGEcX+kr3c="
            }
          },
          "VWzfx9dfcCPmtcXGXn2MVeZuVLKUnvrkprP/zXXPvgM=": {
            "valueMac": {
              "type": "Buffer",
              "data": "Up/omQe3gQY0SoRLRggspU3ixBlhyvcmOOOTJkWPpbQ="
            }
          },
          "VgMglMJ+gAGJP3B8YM31WzqitAF1CkbT20g0vHNcRQQ=": {
            "valueMac": {
              "type": "Buffer",
              "data": "6lXtStbKL2dH8E/ySia4nz/5QbOTI73DLYzvaGhthgA="
            }
          },
          "WDQXL8GK8/QM0d1kyE2Ouvy6YpeaQ82fxuOfeL5XoZw=": {
            "valueMac": {
              "type": "Buffer",
              "data": "1YgW50CL53Da5lERsNE6MF2XYgnvaIslWmR81/jcF2I="
            }
          },
          "WHbKNpaukTwKs4abyvdCDsdB/XU0baDScEQDGtgWVbI=": {
            "valueMac": {
              "type": "Buffer",
              "data": "HAWVGndSe7Vk9KZUBuJnP+2Uj2Y7opG/3gTBBNawTA8="
            }
          },
          "Wm05+Wbd5DkC13NsK99lIuUHrjnF2G80qAHZhh7DbdM=": {
            "valueMac": {
              "type": "Buffer",
              "data": "h3aVIUwB50zF/KcDSQT03mbPdlDaaM4FIQlpEPpapuA="
            }
          },
          "W3Dxq/7z34X57Cg84soilxM7I5+Vgwx3tmYdz7rJeso=": {
            "valueMac": {
              "type": "Buffer",
              "data": "gBTEQgzHeLL50u2jreUy9Zs9aCCptPx2tXTOvMMV6CE="
            }
          },
          "XUJSwTSTIGWncO/E54D8VAodWy8Oc7tCg8Fs1A4+Exw=": {
            "valueMac": {
              "type": "Buffer",
              "data": "ePrVPHMey2w3pYkyGB0w3GO8mHN1A14CAjzTAyi9Iv8="
            }
          },
          "XvPNsdTiUUkIVmZ6bhL49agHp8FL39lSl3QS/LIoFbs=": {
            "valueMac": {
              "type": "Buffer",
              "data": "f//29LhYOjVzEd2CpIf9NwbnKLtQPiRRXgXsGl28N34="
            }
          },
          "X0aapwgxc7z2TTALl1qK4u0SeTOUpgJToR8qsVyuPO4=": {
            "valueMac": {
              "type": "Buffer",
              "data": "+L4E9WNWoomITAplBuSUeP861NctWld6zJXsvFk7BD8="
            }
          },
          "X6q1vBezD5uu1sHHSQBcp00gb7QtqX+koya8nmdvkJU=": {
            "valueMac": {
              "type": "Buffer",
              "data": "g12pyuyEu7bBpbBGH35gyAwmoSEqMW0maeLorfbP/Ek="
            }
          },
          "X+P7Ona+QN/NDauvLyrI3l/FmbKtOowFbueTSpBMHc8=": {
            "valueMac": {
              "type": "Buffer",
              "data": "a/AnSOfttNZJ53FiNPWiJWEaXDFnTiWGK322YTBCmRM="
            }
          },
          "YRlJY+Eq5NsF0yg88S/G8ny7sOGzD8UayKZJLiCHlYQ=": {
            "valueMac": {
              "type": "Buffer",
              "data": "nHc+MY3wnulLcYT1mI9ONR2dCs43anemxntBQ/pWgXA="
            }
          },
          "YjF5hGB8IHmXOMxGG/9Xbnv6y0pvgzTN8UndAiishPM=": {
            "valueMac": {
              "type": "Buffer",
              "data": "uAVV5VvhYUbSve0nqmL2D71WmpGxWtz9TiBn7yyr8X0="
            }
          },
          "YvvfxUql/F0AH9/bZ3W5T4+jkDdTGbxzry9ucqW+qKo=": {
            "valueMac": {
              "type": "Buffer",
              "data": "67/JTNUON+6hCMO/rl4tXfpqhyO/Dh3M5l4yrYfS1Ss="
            }
          },
          "Y0wB6c6+F603QLgZqGIuUe/qDjxAYjyYGLQJPEu0QZ8=": {
            "valueMac": {
              "type": "Buffer",
              "data": "bisgYuLY58aTPz71XHRhLOPVuzJIAq/7IWF3arx4KtA="
            }
          },
          "Y7TJrcQpfKBRDIzm7MwzZuMFieO9iUyYlCb53bYQh0w=": {
            "valueMac": {
              "type": "Buffer",
              "data": "58uLjVAtFsjbMQhcTPPtWWILm3dTzx577z3dmI6KzBc="
            }
          },
          "Y90Bof0r3OnIWuUblXwp/1ETbE7QFKR+KmlsPpZCaDk=": {
            "valueMac": {
              "type": "Buffer",
              "data": "QmU4NFbCYpJ5RDosvd5LQqGOLzMlMgfnq2mXmhhLzUA="
            }
          },
          "ZQP+l3jQo0ilngLN9Lhc+GT6ojMTfv1Eu7R/S1B91Xk=": {
            "valueMac": {
              "type": "Buffer",
              "data": "XYOZsIm8eYfNvaOwaJdfwx+obyhbAZY5iDZmnlUP6rk="
            }
          },
          "ZWQX5jl1HbZKXJ2G//u+GZyOFT0HfGOpNCuwZf2dVu0=": {
            "valueMac": {
              "type": "Buffer",
              "data": "nQSxGmdxDTlIXYUhrNNH/laIqmrWKtVVl9gCO7Zb+I4="
            }
          },
          "Zb4onVxNXzAwH1zLDOmOdhONywDQn4wsEuOjiLGM6NY=": {
            "valueMac": {
              "type": "Buffer",
              "data": "RbbYKSnj2AX22kxfMY79xKXaBMSGHxowBIjnDe6bxDQ="
            }
          },
          "Zuz0cJs2vY2t3meXKb1AgsZ46uzn+BusV5h7dmlpU4I=": {
            "valueMac": {
              "type": "Buffer",
              "data": "HIqu37gwKsNvcqYkvNR8333NmGb7b9rJaroN9ZO/ptE="
            }
          },
          "aFcp9fism2/08KoQ1SUkJ/VpSXGBLa3oUZi/HP1ltrQ=": {
            "valueMac": {
              "type": "Buffer",
              "data": "vQdby7zJOjeJZxcsqbTxbppA9xS4XK92CiQwED2NrW8="
            }
          },
          "aOys2eOCnVBQUl5RX7hwCjvMBhv77pFvVRrnmvLrpQM=": {
            "valueMac": {
              "type": "Buffer",
              "data": "jOYSHK8nTnDFBizNlVSPOQLRJ21GSRd38deonWIiktQ="
            }
          },
          "agUkNBC2DJ55+VKxxLfOqF3Hw5yloeww+9g/ItjWpTk=": {
            "valueMac": {
              "type": "Buffer",
              "data": "n+1U7EY4jmPpzgHLq3LTrsgCeI2es8s1SRFfuteRA/M="
            }
          },
          "bBEGD4BeAs/NvPPkyvngKn+mVEGGwUtrJInikcfB2F4=": {
            "valueMac": {
              "type": "Buffer",
              "data": "q4QzlhZm0Va0xe1WVhjniVmd+P6/zqYxi+i9TRPrcgE="
            }
          },
          "biUJi0uuGXPHaiRGlBb46l+OJckkADl8KFuQl8q345Y=": {
            "valueMac": {
              "type": "Buffer",
              "data": "VdP9CRqSVJ3R8yHQL9sPbGff8q4gW9+LVjAhnJfYMeE="
            }
          },
          "boYpgjbHqBXD5Fu8CJjBzchikXfvPiFF1nAtGWK3PNk=": {
            "valueMac": {
              "type": "Buffer",
              "data": "LBfnS1AMiu80h+beNMOZ2tLbRDPhYheuQGO+p/gyp98="
            }
          },
          "b1WhfwR9jU6mKjWNip5fw25ezxtGzl8NR/S2DgmTX7E=": {
            "valueMac": {
              "type": "Buffer",
              "data": "Fqj3BWgrItuUkMUso8GURMQ5kLr+THXEV2JEyU1I7hY="
            }
          },
          "b86RWL5zjWNHjOtZV6R/bDeCqqlm4ONztmlJdFgtUD4=": {
            "valueMac": {
              "type": "Buffer",
              "data": "X390Hh2B+3SLKCSpeR9/H6G3zMpte8bSxvl9Pin14FY="
            }
          },
          "cClMHmHuaMGrGEuuww04N7skzO/98gnqi1/V7gSoE4A=": {
            "valueMac": {
              "type": "Buffer",
              "data": "PQ1s9l3kDb3tgd8A6ddwBUmY9k1YQ4w8oGMrvDRInCw="
            }
          },
          "cLlqiOtawkXa9Im1cVhIPp8PedjStwDlSfvJMrYFI5c=": {
            "valueMac": {
              "type": "Buffer",
              "data": "FbY/70ktK/b4beFeK1xQhSjMg5pv/rb+am5mWkz/KSc="
            }
          },
          "cMmSPvzeTm45FybGR8ohvXg+to0lJcWzSSDCFviibTY=": {
            "valueMac": {
              "type": "Buffer",
              "data": "oWitCPia5ZF12moHx4XG42XVxTK+xcTp3qt7qnrqCyw="
            }
          },
          "cU0A6pELYnkPwijsMuoETsKekYSfd+H393t55arzjdI=": {
            "valueMac": {
              "type": "Buffer",
              "data": "FTaviMOOSbN/GY1COQdh+EtulOuK6N90AOtLvhUzsy0="
            }
          },
          "czmrMDEdfS/6C40a4c70Ckx2xvddRaSHs+ousw4CqQo=": {
            "valueMac": {
              "type": "Buffer",
              "data": "l1vMZq3HxpJ0IsvApH04RpWUjmdXAW0sdPVu7GxYv64="
            }
          },
          "c297MX9gi3wwWShAXFjh9Bnls22zw2OYdEWfVgyOggc=": {
            "valueMac": {
              "type": "Buffer",
              "data": "4Guph9hxLfgaPrfkmciroMXS2sYA/Ifs96hSsLbdy0U="
            }
          },
          "dDQ4D+B9XuVTJYlGXXd7Pk55jooF9hkgfGczz1oFQl8=": {
            "valueMac": {
              "type": "Buffer",
              "data": "h0p+lHvmWr4W9W1NFZ8LJeo+veIENPKzc6KiELud5vA="
            }
          },
          "d0/fWYd0HFyfhrDU4SPxyN0dLtPEKC5CmyhCAjfA0Fg=": {
            "valueMac": {
              "type": "Buffer",
              "data": "Kk2TZOFjfpJlOVPJ1HklMlzUTFE2/zp8csLBy6M3QhY="
            }
          },
          "d7eVjomoL35tuePNS3A/lIu3teYbKKiLwaJyWETylnI=": {
            "valueMac": {
              "type": "Buffer",
              "data": "3XN5ikikoIxJe1vDnd3pURbX6jlCDvu3g+LVJddSXo4="
            }
          },
          "eY9gJ6+3ilynEf2U8vBYtrfFQNs587Tx/kq7dFFYUtQ=": {
            "valueMac": {
              "type": "Buffer",
              "data": "boVhZIej36BIE6zMoITd1QMOgfpFYmMjZpJpCDrpdwM="
            }
          },
          "e7mvGELhhnfiAd8rUmfTsDTAS645F55RLU2ZPFB2c0Y=": {
            "valueMac": {
              "type": "Buffer",
              "data": "tYlVnpi8Y1AuEKQcfjbr9eAHlKMaleUPQiL16dLFbAg="
            }
          },
          "fL2KzOVg5OaKKHbA+g+QglPdFAIhY6cPHsyHj0Kc61M=": {
            "valueMac": {
              "type": "Buffer",
              "data": "tPWU1a4p62rYML0cd08jP9+byBnhSJADJDssLXeUcuY="
            }
          },
          "fQihx5+BbXAX6He/QKy1j5+Hde4xy0PlOWuS/0q3/NU=": {
            "valueMac": {
              "type": "Buffer",
              "data": "xRo4x7Yc2aGD+mD23l8sQvK7QrKeWFqAxYJODywGd9I="
            }
          },
          "fR/RQ2NSpM2+q0y7aJ9uMyaFjF9CHfjASOyCWvnVq64=": {
            "valueMac": {
              "type": "Buffer",
              "data": "yzveMQqElYKUzAlO/U5xar6TYsQzxC8YwfWQsX9QY1c="
            }
          },
          "gdbrexUdUthNygfBRyTQ7rs51QpwIkz0kpmPmD/WOZc=": {
            "valueMac": {
              "type": "Buffer",
              "data": "LmiHh1aSHPnXS6BoMZuJvQWqJySr8qd7YZw26PxUq5o="
            }
          },
          "gzCIGnp1aihrhw1ZnkHc3oY8rvefCOA+PED7Na8tKhs=": {
            "valueMac": {
              "type": "Buffer",
              "data": "qSLot90glWZ/wFHI/B4TcATjOV/dmAFo5zkGi4jxupg="
            }
          },
          "hTGwIlBrvGU/aCwU9tNOeKql+jOyyujcjOlBAehqwcY=": {
            "valueMac": {
              "type": "Buffer",
              "data": "FfrHjdNSrmgHkiviK4gJgfUixCt0MgXAbRFP7KKWn5c="
            }
          },
          "hyzNCzm6F45XovZK8Lc5YmiAN8un2WSC4HY4+BIFkR8=": {
            "valueMac": {
              "type": "Buffer",
              "data": "RN5BrUSCXZHhBCHhcvbqPi0ZR7fb4FRVZkJy2N+GdgM="
            }
          },
          "iZGyUYQopWkt05Ry4NQh9hciE6XCldJUoUjSXh8m7os=": {
            "valueMac": {
              "type": "Buffer",
              "data": "riZNZ/5UeNoL7RWMkdo8ZdMTQHLDt0snDlQrpgj/Xg8="
            }
          },
          "jGtSjKS0M/aX1xWzZTPw0Gqgy85oZDmLWfOVt5/q46A=": {
            "valueMac": {
              "type": "Buffer",
              "data": "4yKjFHwSRMWCq/x3fM3tOQVtBoqVYiwS67rgtLi9Ls0="
            }
          },
          "jSxS9Uk/10h7eg0iqvQ+VlJ7rghmU3+eBZXy8jyEBjo=": {
            "valueMac": {
              "type": "Buffer",
              "data": "HWPY5GIbq2sx2wbK235UZHeZqVQVJGx9hUFwOldVUeo="
            }
          },
          "jzVq2mmDB2K8bGWn3La+kVupiDhmQSpqDB0RgSdV5f8=": {
            "valueMac": {
              "type": "Buffer",
              "data": "KFW5hEuhkxWPZOslymjKP9XRPcwI/u52qshnzvAHncc="
            }
          },
          "kCYUsOBcFIBl916Iys2kdhinkJ5GOPLmk7KUOdvN2X0=": {
            "valueMac": {
              "type": "Buffer",
              "data": "Vq5BpkPCl08iHxr3ytYJTRZH4nuJd8RmZ2OBbyXG/ec="
            }
          },
          "kHgmGQxpaD6xndYVxWysFkGA+gK8RseIOwBx8lSlP0U=": {
            "valueMac": {
              "type": "Buffer",
              "data": "6nSZn5QNNzv/9iLVrUv8qlLmhy/XOTZeaQ0XumF4n5Y="
            }
          },
          "kJyb0CgXTiQcfrG1sNMbfiT9oPm3OnucBWjN6waYD6I=": {
            "valueMac": {
              "type": "Buffer",
              "data": "TGVcqw8oEQG30O0UrKavxcVzJ/z1LXFibFt3VUsbnMQ="
            }
          },
          "kdQ/KOtqMmrThp2doraQNmDaXnK0omDcv5j474dyyZ8=": {
            "valueMac": {
              "type": "Buffer",
              "data": "Fe9XsD4oKfCYAJM6NvE6WDBz4Wt8GgXIgWdEcu+LlrQ="
            }
          },
          "k1d0S9nP8gK2neXgxLX7gu8uBj+DCvhoDhPG7pc69eQ=": {
            "valueMac": {
              "type": "Buffer",
              "data": "u1vwPSV7TFVS6nBUSc9QTxaiV41q7m2bti78RSXjFaw="
            }
          },
          "lLmqe4GrmraMd856IcZ3rTziI/0aG7r/xpW5d+BUjl4=": {
            "valueMac": {
              "type": "Buffer",
              "data": "92dKJ+R+fqhFlpbe3lAFL6qCEHFGV5swGKHUnvQFuJo="
            }
          },
          "lOYx0pb9JbPl9n4wt+piVLQor5nzZjEcuf2DrUFF5Oo=": {
            "valueMac": {
              "type": "Buffer",
              "data": "/ihu1AUg3yCbM6tHcP9kq4MZXdKPfwdAiMzts0DYjqE="
            }
          },
          "lnWm65xoutdPkN0K+jXbx7yNqsBfUja5tPdRnxmEwcI=": {
            "valueMac": {
              "type": "Buffer",
              "data": "IkbovB7xXWV4tdPAQaoRsmH3QFlQ0STi9J4b00J8i0E="
            }
          },
          "lrxvAvXWZmKwXtuKAuuakelgst4CMoojAV+JuE39zbo=": {
            "valueMac": {
              "type": "Buffer",
              "data": "QGmkhqrtiJCm7jBNeCwE6KHqsMqjecGlN63mMbiImLk="
            }
          },
          "l7Lzi4hqDNupfYwvhr9xkGe6bPIrmmeGwBhP7c8bZ18=": {
            "valueMac": {
              "type": "Buffer",
              "data": "KLaOpr/MVLG0C3+308l1BWXuxzw68GbWVk/sjDK9cV4="
            }
          },
          "l8tXZy+12U2PU0p5Q5alizKyGX7LJoEdpz+t0J92A5Q=": {
            "valueMac": {
              "type": "Buffer",
              "data": "4COiF41gN9Zjewxax2LV1nG45I8XvD2PXdyhUXgxjTo="
            }
          },
          "mJxz1NW6ZfAuaQWMf4x15ymjXrkZ++T9UmattAJ3fEI=": {
            "valueMac": {
              "type": "Buffer",
              "data": "PROVncG7bip5RBCzsmaDU9Fw2K9/kSuOJbOwEleSgrc="
            }
          },
          "mh9lBaNOXaFEfYtmeP1lKvRtb/W0CBubwSapEW5ODAY=": {
            "valueMac": {
              "type": "Buffer",
              "data": "wJXM5lF9shxCKKM8DlPcwqWxWOLLbt/OH08o/ZLb6uM="
            }
          },
          "mp/L0P6iA0yxMeTYg3huriht5sKO74nSr6H8SMI6XV4=": {
            "valueMac": {
              "type": "Buffer",
              "data": "HaFGwkkcHj9XxTC7VvFpIVleQyVKLuWlnnJ1nJ0Cntw="
            }
          },
          "mrVDGnQsmyUI9wdfdmA0PTJAJ5z3Jvy8te/GgNps3/Y=": {
            "valueMac": {
              "type": "Buffer",
              "data": "TeAvwHL01N7Ki0E3H/YDi4daIr/ajh7VHxgASRI9v4U="
            }
          },
          "m1Sps8V09K9UmPoyd99Uq7ltdJVoou5Wfsel3RrIvEo=": {
            "valueMac": {
              "type": "Buffer",
              "data": "uxSJJMLT/knD5G2TvYETuZg0UcBUs0Rk3LVACgsffsQ="
            }
          },
          "nCsc/IXPgxA9X4WLDulI+YTXH01AZfSHHCbUoX2xG4Q=": {
            "valueMac": {
              "type": "Buffer",
              "data": "lKVSsjdeY4WS6zRntI7ho11K0ppbzO1tiIlKeZlA62w="
            }
          },
          "nibxgQSPStTIzj1jSvEVxhGUxm7mIBHNI3oiIjVvwdc=": {
            "valueMac": {
              "type": "Buffer",
              "data": "OSIilIGrm02BhOEGmxgwbBNEYCQlzLPaXVmq3rQyfKM="
            }
          },
          "njesmrKYmV99WpX4IsNKlgs4vgVtAzQpV2JH7cmzelk=": {
            "valueMac": {
              "type": "Buffer",
              "data": "aqUk6owBkrMJvg7ux7eCGuqJBWiBpMTSGzv/V04N1hk="
            }
          },
          "owIKk78DifHBUDKdoVd6gT1AmuAp1gRMAZ/VYIxxHYU=": {
            "valueMac": {
              "type": "Buffer",
              "data": "XcPWKBIEY2wx0TS7U18H/B4jVDDRh5x2p/RidU7fp6Q="
            }
          },
          "o78aiApydQfdHDU8aRC/y/aWDPlkk6o4AoHwMJk0gQM=": {
            "valueMac": {
              "type": "Buffer",
              "data": "Xwj8T7Ay26GBfURKXG3tNbEiv7eFeP7Q9Q0oxUxeVYo="
            }
          },
          "pDAoikOtmUUyMmlFhpQw5tG2Qkm5CWGyg+JBywW2crg=": {
            "valueMac": {
              "type": "Buffer",
              "data": "5+Y+uxGvWz2cZO8nyuL4mp0g2Ntaj20qAtls8nJ+ILY="
            }
          },
          "pMd0Qsb9iE8B1psf23C2zHw8zwGzPKeddRNHC6s2htA=": {
            "valueMac": {
              "type": "Buffer",
              "data": "OYLw6NSFcMJjVATNcyRTGKwuBBwDXAtiYBENc5Giwvk="
            }
          },
          "pSWPgfwnGvJL678cWB0neHfwitlo+KZsf8q3NR9pl0E=": {
            "valueMac": {
              "type": "Buffer",
              "data": "iulHWAlv7uyGZJbbXh+oeBLjSXPdH8MMJT53IWnRQhU="
            }
          },
          "p3I1Y3aQaHKzlKDlrYOooIo0jVQVLXzJ/bHkQC4sAKg=": {
            "valueMac": {
              "type": "Buffer",
              "data": "a0JX5R37Q2caHQfTXSX265F6myipcNu9+zFz/f7wbX8="
            }
          },
          "p3pEWGqnh0Jq09EJ+WFByKzVRqeCaE5nRqeZ04K8YYw=": {
            "valueMac": {
              "type": "Buffer",
              "data": "59FxHBITHCWu/X5fwOTM3vdyUWIXaPdQDU1mBzIjMPk="
            }
          },
          "qZCiKhndFjFAvr2dsHMy+qSJ7ilxNcj7ThFl1jNyTYA=": {
            "valueMac": {
              "type": "Buffer",
              "data": "u4UYwcA0U5znM94nRxNuk98h7im0JszqN0DdQqVD6eA="
            }
          },
          "qZXc3ylUim9mlinvncuwPmL31+yte8yibik+EhHhL9E=": {
            "valueMac": {
              "type": "Buffer",
              "data": "PYR3GmpFqG+rBPxsg0ihqmDXNCf0ALQWdeT6lxQt3XM="
            }
          },
          "qmmgWnTuj6A6iZPoLCYntXjcrax3Bsdu0kR4rykSmEY=": {
            "valueMac": {
              "type": "Buffer",
              "data": "R4P5N7D7WfNvBDOwooeaOTyzsoCu2bG9E19RBWWECMk="
            }
          },
          "q6PRtxnzhjp8WMBfnc/wpwvix/gbSjn9oMalwNZc8p4=": {
            "valueMac": {
              "type": "Buffer",
              "data": "/w8hK3P25ssJIddXeMsAsEbxaUOStPCJuhF8h7Sxa00="
            }
          },
          "q+C+IoyiU2sI1bWqnmECLfsmUzocAszg0w2/MnVWNGs=": {
            "valueMac": {
              "type": "Buffer",
              "data": "0tLoL38ptA9B5snClSLnqxnn74Mc5Ps8XXxXblHkA1U="
            }
          },
          "rE7c2v3ygYNZ4GeslqIcjJr5zm/Op0TkVSy5GTsCG1w=": {
            "valueMac": {
              "type": "Buffer",
              "data": "+iMsWS1Cqsg6qqGm4WX4OtvV5J7knRrB/xDfxuM6ry8="
            }
          },
          "rUjzMfC2p16ia6WvxXq0FdEf25q+HbDl3Uru24Hwzzw=": {
            "valueMac": {
              "type": "Buffer",
              "data": "JVvAUPh33I3CEDBButmn+sZjEVeQVLDYba4xDhmybXs="
            }
          },
          "raDrkT5rYOVI6asRo7TUSsLbQCYKnRCbPXffQC945fA=": {
            "valueMac": {
              "type": "Buffer",
              "data": "LXn4XNKR//+ODzLTtP0bX9k8EWOhCrb780FnNGk+h2w="
            }
          },
          "rczLmxnvX73u4405bBkTHgdkZRo6UfqpXgehRSv1MDk=": {
            "valueMac": {
              "type": "Buffer",
              "data": "N5W2PIv2lteHvYjSkodvsONXrdyiM9HTUNpQYExyGns="
            }
          },
          "ruxtaad9iAHXmkIfceMf7ssLhJXHWLpX37tJ+DGAVMA=": {
            "valueMac": {
              "type": "Buffer",
              "data": "CYNZtmXRGPWC2wF8qXm9smrAIVVJ/RzVhTvI34VPqwg="
            }
          },
          "sCXB3NPRqY15Z/aEq6hIwrGd4GmnxDmnw2iYn9ig8ME=": {
            "valueMac": {
              "type": "Buffer",
              "data": "yIkqAbXP84pJaGZH7oWtVg3AD/4lIhpsV0VvpXsWKPM="
            }
          },
          "sRgEP5r02XTHrbe53NBqJ/8W1CS5txg7zEuMY0pqW/k=": {
            "valueMac": {
              "type": "Buffer",
              "data": "KXbLzfzFpTtmLQ9XVEKnfnk1Qw8wjf2JPP+FOX+OhUM="
            }
          },
          "sb5ISH7iRgmoWjZWIuPpowFDLuurHYJzjxyfwAe8E3g=": {
            "valueMac": {
              "type": "Buffer",
              "data": "K6awUyeDH3/vf+RY6vGLDAWxZG/MqKoc6vl81FPTryo="
            }
          },
          "soJKUnR51HKcKLMDO8nB7yl/RcsgyTduR1HLZVkSbPs=": {
            "valueMac": {
              "type": "Buffer",
              "data": "EpsTU2Oa0MZMvn9UKpp5LCEGEVzA3on6qXVlJKHhZOQ="
            }
          },
          "sqVkB4gLbVZaf+vvOWhFD8KW6ag7f4itMxNVi6y3Tvs=": {
            "valueMac": {
              "type": "Buffer",
              "data": "CTgJk+/7JD7p7Z9dmqKqH0b9lQAXwFvjMKNdElbnV7U="
            }
          },
          "tjL6F/SgV5Y0s45Y7gyowU5w8F6IUkL/5Tj9nU61Lqg=": {
            "valueMac": {
              "type": "Buffer",
              "data": "Iherx/R+mbJcMncYp88lJxqBMasIKNLSpR5eBFsQAEk="
            }
          },
          "tvfMznVdVAQdmxH7cZf/jJwsS4vH3czrUBS08eAALFk=": {
            "valueMac": {
              "type": "Buffer",
              "data": "Fla+523GeASCDw8Rr9NZvZtQLnFf6o1YWyyWlCGFKWc="
            }
          },
          "uEz7zQXcFsejtJGUy9jeM5o8eUC6DUMAf/uF0KHPEGo=": {
            "valueMac": {
              "type": "Buffer",
              "data": "zhhfOaW5XsK7IFUHUkXtD0aPSE07kWM9LOas7rvgSxY="
            }
          },
          "uIfVGR2x5uiCXjY8I2BFlXuTq6Qu8EX66cK2+fPDQcY=": {
            "valueMac": {
              "type": "Buffer",
              "data": "pLngEHrI1AOKOnmA9eyM05SO0Jq50+g4s5JmhhuA9zI="
            }
          },
          "uUPsf1sTTWb2KQmcOK17xQiKu99H14VAhVpPQEwv9GU=": {
            "valueMac": {
              "type": "Buffer",
              "data": "ErsTI+4gGVQAFhTZhBZ6PFnHdOzt8/2HnLmNRIstk8M="
            }
          },
          "ueoh/PuszB2yO7v9hJ9xjQ6GtlRfs7gU6Fszs3ZR5bM=": {
            "valueMac": {
              "type": "Buffer",
              "data": "AKPRydqJf1lb2nKaC28Qp05Ul317wkwTkVm1VLdx3cQ="
            }
          },
          "uz0J2ZblJuiw/sKs6FUpCdtqctPAhXLgS7wIWZAghRY=": {
            "valueMac": {
              "type": "Buffer",
              "data": "OR0VoOQLk4obvOn287BIq8xK88xRmSIXZukR5BXI+EI="
            }
          },
          "u5GM9eacNV2w5rRoGIRrrXJRRf41pWp5VRNYz5CIt0s=": {
            "valueMac": {
              "type": "Buffer",
              "data": "mCHFjxN3Hjfg+A+q/L/tfO2uk4s/NlI/8ecjHCVxPcE="
            }
          },
          "vPNc8achF1btZFWejhiUw5zZLShx+iAgkpR2zLRCDXI=": {
            "valueMac": {
              "type": "Buffer",
              "data": "N0lOYtJTEZmFPz22WHb/CMqYlYuY5dTSGVLijTV8VY8="
            }
          },
          "vzzzWl3pbhzDKruaUL/aEhzEhy7VeqYnotYBfj/gnFc=": {
            "valueMac": {
              "type": "Buffer",
              "data": "bwHPCwyMnxf+9UlqjTEAVs0IrBc2DABnm3g+cCIBSJw="
            }
          },
          "wCszbwrl8ItiNgapDbCv27jOEgv5SGYqVfYEXV665+4=": {
            "valueMac": {
              "type": "Buffer",
              "data": "NrCsXd1wvnSRks3b7DPFz1bd6HBDHNUPj+uzWw9I4Qw="
            }
          },
          "wdxf0UEg9Oq9HWdB7LTMBA5mhYOfxJhmBrqORY+7YaQ=": {
            "valueMac": {
              "type": "Buffer",
              "data": "nB0pvrHa9i112KgX+CaprmP/0lQTKR2dkmEdg6meP9A="
            }
          },
          "w1ph1oJ9aUArd+ddnPs+i9vOdImcQkCUhRH32jDuuzQ=": {
            "valueMac": {
              "type": "Buffer",
              "data": "YcKIVvz8FwhUXMT8/RSA06B1GypVpmwlzGHUxaoyLU0="
            }
          },
          "xSwEbIN7D2qc2UFdy+a8GNs4uD3J8P6HUULNZPnE83o=": {
            "valueMac": {
              "type": "Buffer",
              "data": "EXAW8ZR+7RiWPCziZAy2egspCA45JjiWVUT87Qx46EY="
            }
          },
          "xVyHeIIfmwttQxM1HzePN4UR0iLEhc82Nr5IOZoEcXA=": {
            "valueMac": {
              "type": "Buffer",
              "data": "l3nq9y1uNgd1E0O1IYbCh82I3J44muQE0K9QJVYvuUQ="
            }
          },
          "xYmjlOVNnlglVdIG6JvbVavfGPjQrbQOADBQoF4MuMA=": {
            "valueMac": {
              "type": "Buffer",
              "data": "BNj0OuUink2+wrDhs6754cgVGpOD4C3cgnt4NMrO/qU="
            }
          },
          "xaaTIfpRImqOVa7E8OfLRgyN8W5h1qtfWikpQ4y38mQ=": {
            "valueMac": {
              "type": "Buffer",
              "data": "cgG0L/GHhKDn9IXLy650xQ80c9PGJX0EE+zgsHVxS48="
            }
          },
          "xps4jXTmcazENaDEH7k3NKwz3JVI6eNfn0EbshbyZjQ=": {
            "valueMac": {
              "type": "Buffer",
              "data": "mz1yVs4x40F22bsIkaXmUNRSmS54lXuMCDCkl+ikU3A="
            }
          },
          "xx0EGiJJU1yQBqSO9KQlSIqYAZwoWMzN6kg73IiXRNc=": {
            "valueMac": {
              "type": "Buffer",
              "data": "zHCuHnC88MZej9xbxcpca9ijt26NsQaAL5ptvETe8Fs="
            }
          },
          "x3zYuqTFQPaF+6ptSnsh3Hf/WhOwlnRalWE8Ly4iKJc=": {
            "valueMac": {
              "type": "Buffer",
              "data": "gZpIZ4D1xlhCnP+cl8xeKoAfRXYPBXjhubZFHAKPCGs="
            }
          },
          "yAmv0kNYempvWffU3gKcmJbYDHJgXc83udGhgS2pyh8=": {
            "valueMac": {
              "type": "Buffer",
              "data": "zvrsoj14W5FEzihEH98/bolShisvbh06qBU+DrJi524="
            }
          },
          "yEbcVqL6qAtENS9qJkV6XJ5+9ow+lfDhjhO1t9h3R90=": {
            "valueMac": {
              "type": "Buffer",
              "data": "6c5U4dKL8NOyz2zKQ3eAlBf81vvJ5FFRROeuvzWnOus="
            }
          },
          "yJ8EWI5zA25Wk1UX4FQlhQuU6b40G73fi680LPXtZtk=": {
            "valueMac": {
              "type": "Buffer",
              "data": "dRlrILcgGLHpgRhkdhLOVY+La+KQRqDROJuFzrX+50A="
            }
          },
          "yZiSBYgNS0EEKpxRrzxiyBUFd3f99VrcrwPDsVOYJyw=": {
            "valueMac": {
              "type": "Buffer",
              "data": "zj62bJ4Sgm9UQgw2REebuwuQ59JjLSxT7SSf75mGGSo="
            }
          },
          "ycJb+pFrIbK0jpPvnWr4DNaG1O9UVFqaBSCwJxLfGYY=": {
            "valueMac": {
              "type": "Buffer",
              "data": "JrxAyUpzHjUM49Wk6K/kXRz0SDaM2kRBxjn0OMkZNCk="
            }
          },
          "yn34iFOfdOtZt4jLy1HR5CJlUJMr4dT1BvEOMRb0ox4=": {
            "valueMac": {
              "type": "Buffer",
              "data": "Uik4lPrkuEEhZPlnhl4T/7bwy1e6/d4WrROFCB7ixqA="
            }
          },
          "zPNgPcJTJy53F0Shnfh4YziFtScvVMMvBVvc3ZsVtP0=": {
            "valueMac": {
              "type": "Buffer",
              "data": "eJRaQ1+UXJv+tIWoWjuEob7IdVKnolebZVFDR/JZeJ8="
            }
          },
          "zjpDtBe07BOtYpHplXHQrm3Qx+sw+14caKLZ7ceUnho=": {
            "valueMac": {
              "type": "Buffer",
              "data": "nXH96Pv42E3ZwzpAfVfWBSAODDf/BFvC1AXIuGQXR2s="
            }
          },
          "zxp+XqFJc4y37fgM3PvdxLqOu8a2YA0+JhPafIGaw2Y=": {
            "valueMac": {
              "type": "Buffer",
              "data": "6+ToKm5C4c7Osabz5P4Rwuk5CEeXarSg/fAKaDUb190="
            }
          },
          "zxtzDnvB79mzcM4lxBsl88s2DwkNjj1zWQ+VgOFhVds=": {
            "valueMac": {
              "type": "Buffer",
              "data": "pazo7cSxZF6W/87DkFB8vXsoni8DvQHgwC5L+9srOTA="
            }
          },
          "z2RGVaGuP04VV4Y4GOrnbde+jktBOxfXT1znSmoosdU=": {
            "valueMac": {
              "type": "Buffer",
              "data": "y5LqHhlW5JyArxwSyTvOsopvvSJxduCe6M8oc+ehH5w="
            }
          },
          "z2yAqNy3BCqgP/xpTcVF+2hjBUtCB8velJqrB7+QBtQ=": {
            "valueMac": {
              "type": "Buffer",
              "data": "+59Jjk4/aJnE3LYx4oCUq05cd0z70Vjn2Fk2QMhYXTo="
            }
          },
          "0FUuPcvTHSSpmEoLjljrge6WlpTLV5GtdnucNlZwqPI=": {
            "valueMac": {
              "type": "Buffer",
              "data": "vn7xeFRmMeJTpFmHaeRKaSN4MqdpHguyMci1zU0jRrk="
            }
          },
          "0b7ygfJBehZwrYE4jwVGqD2ffchWQnC7ACrl32g/aIo=": {
            "valueMac": {
              "type": "Buffer",
              "data": "VfhKEpkoWjQw+isc0FH6WbZ4L5w+KEHctwFeDqtbZLA="
            }
          },
          "0lWirk+k7/ePWPTI1p8vyM1WCi19VKa0iCkHhdVzg58=": {
            "valueMac": {
              "type": "Buffer",
              "data": "QjaVZaOWApbcX8cr5za9WO8EsVkNT8VX7A5jHKP1RzY="
            }
          },
          "0yTvVU6vxJKGmaW8pm+55/biQEQT4YJhLYcLyp2UOeY=": {
            "valueMac": {
              "type": "Buffer",
              "data": "O8+ZG5x6puuItGDpyDfkltDXxlnUDU2qKwCAhXecM90="
            }
          },
          "1HdGD5qqlve75DD6PMV2lsZ08fRGWWzpM9yimx1kkrM=": {
            "valueMac": {
              "type": "Buffer",
              "data": "0lrKHWzGQYUt1VHNW19eq1yXZvv8i1B5GkcUnZQ4ZxU="
            }
          },
          "1Jw1r29z+iSmNlkX8xijblg+SMXIRXGNKo8eWpvAY7w=": {
            "valueMac": {
              "type": "Buffer",
              "data": "79icfRw2bdsfPtKZxdTp5u3waRZ1DIJ/Zeyo3xYJdYA="
            }
          },
          "1NnFirb1Xv4bcgRphmYHO9ma3oijBd5UIS6Crrj5PDk=": {
            "valueMac": {
              "type": "Buffer",
              "data": "y1Yo+1hjdO4JhibAdlWL5xlqLZtiVQcSd3OnwwPcSls="
            }
          },
          "1QyjjBs8d/lkmIvojIUyzN+cZd6Q92begTabYCI954Y=": {
            "valueMac": {
              "type": "Buffer",
              "data": "tqUCwd/6DF9ktvNlXUHN89evYUQrsyLm6zMGvXeSMjc="
            }
          },
          "1XJtjGQ/qM1CIsY8x+h7J+9hdm7PtVScHhpkRwRv0q0=": {
            "valueMac": {
              "type": "Buffer",
              "data": "BE3CjiP91jgU+iUAyQLp4QcRju/Ea0b90HCfLmXLVpA="
            }
          },
          "1bi7nNEGQnXOMD8GluEQJj1IsfWmjsXG1blKSYxf+s0=": {
            "valueMac": {
              "type": "Buffer",
              "data": "yBH58WYPT/mrjQcTnN8/4r6NMr3bAU2larTc/3c0SHs="
            }
          },
          "1gPZ39tjXV+/yRQyLXG9a9YFibXH1UkY2gEcAqlXEDI=": {
            "valueMac": {
              "type": "Buffer",
              "data": "cFvtBE0SA4Houoohyv5cHtQF1xZCYriPi5V3WmAJu08="
            }
          },
          "1u0/OS218LekpBNOnlpVyCZq9uvZxiPI6hrbPljq2B8=": {
            "valueMac": {
              "type": "Buffer",
              "data": "Um0dYvRr68DNjWcwjoinJxZDPIfacqt1SxAUWF+d2Dg="
            }
          },
          "1x44dS08HGrXOWl7PFQm8PKllAy6Xv5zvx8T2AjtgQ4=": {
            "valueMac": {
              "type": "Buffer",
              "data": "OThKc24sI6cM6o6S6UkrNETH6b6OnAh6T4rEbcX/ask="
            }
          },
          "1yOLk33Zf2JOinlSf3vPitmwE/lpt8CdjzPRX1SPC0A=": {
            "valueMac": {
              "type": "Buffer",
              "data": "aRWkpr2YFCHg8IUXVQnCAFFN702+y+iXZ7ik5JvyY/I="
            }
          },
          "10OaURxkywqexnp2XmR9IgOvUtiLdw0rxnwQkBCWWIY=": {
            "valueMac": {
              "type": "Buffer",
              "data": "hbHA6Pd0SKeuPb94yh7JPAsDfhYQe8G/sOAdeX0PQFc="
            }
          },
          "2EAL0ZPqcA8X4wGjHTn30sXll6zIJW9+PIocKVTbsus=": {
            "valueMac": {
              "type": "Buffer",
              "data": "cNRrWAQ9o9jrjAUoJ5iEj0CyGw5ksyDNrwtyp8DdCjM="
            }
          },
          "2i6x4LyX+7gwzJLPj/8nSwgOWZWsHe0aIIGFvyuP3nc=": {
            "valueMac": {
              "type": "Buffer",
              "data": "GjK6r5yqoLfTB/pLh5nfypDoq/Ni3VctYIGv19m8i20="
            }
          },
          "2nmZ+xSf+EgDw8oh3cQJq8lk7CGfdrDih9FYR5y9dVs=": {
            "valueMac": {
              "type": "Buffer",
              "data": "nTmMa1Vc5MsGbciIXiNZy7sMH4U2FtQn0Xn36fbW8JQ="
            }
          },
          "203hwyd5yPPTzM8uK/s2IXdtBxt0Qwt1UaX0mfaXBWk=": {
            "valueMac": {
              "type": "Buffer",
              "data": "d4w94xQeEPjRXG7lIZ/ZyqXX87GBH0yPQ9a4q1/MfnA="
            }
          },
          "30UZOeJohLjT3El9gcT8QCgkl87MsIeAlB13avGPTpM=": {
            "valueMac": {
              "type": "Buffer",
              "data": "MVt/tHqzs+UIcBitZkhBuU4bsYWt+AXm23ZFg8OuSvM="
            }
          },
          "34f5zYU50DR8xWfSqIx12B0FluINo25lql+znesMZQc=": {
            "valueMac": {
              "type": "Buffer",
              "data": "fnElFN9t/ITRlNNGEJS5c3OSjtuyUHBbGjmJoFZBCfo="
            }
          },
          "4Iyz5MYCEQ4cnsZMtz5rxav9JtHI3GDfLZBCH8pz/1g=": {
            "valueMac": {
              "type": "Buffer",
              "data": "3p/bKXTz1kDfW2RIxCLUXQ9m1XBtruemSJlb21Ij6h0="
            }
          },
          "4pX3NByXHYmSWtBkR6ReWy4FwwFuyT41ogVmxmZjJTE=": {
            "valueMac": {
              "type": "Buffer",
              "data": "2YrGDvh7ZFjVTk168phKq+/byiStF+KI/d5FkzyhzKI="
            }
          },
          "4s/H0sapBRgssuFieZLTkkL89k+NfWBlnCAVk23Ax8M=": {
            "valueMac": {
              "type": "Buffer",
              "data": "6hnyk+4zrSNuCbp8vXaYq4Z7Aw6+h3CKvvecbDXpBuE="
            }
          },
          "43Q3ZAFh88s2wua3p5nPvEQjhn5a19yrnV0SXNVgAF0=": {
            "valueMac": {
              "type": "Buffer",
              "data": "xPVUDVG33kNNmiRnMA5yjC0aNLp0uZ9Lf/uhqh1sOOg="
            }
          },
          "5F6fH58NdB5LiPKq6zuNNaRhSA0qyFC7/A9sfX7fjZQ=": {
            "valueMac": {
              "type": "Buffer",
              "data": "+7KrFvTBHhKKKSNPqSF9D/D1y3htxfxihna5tNiGVPI="
            }
          },
          "5JbHS5zT2lXbAgVzP1mkqDQ5mJUwqOyAUdUAbGFdy64=": {
            "valueMac": {
              "type": "Buffer",
              "data": "UZCmPzwWBF2aLb1CMtZUfLQpxkvfFktpcNVu8J9cfNY="
            }
          },
          "5ZdLut2ksbleIfPJ7KFiiOrJCTjPi7Ffq7DJNF4RSNM=": {
            "valueMac": {
              "type": "Buffer",
              "data": "NKYNNwJ2T2GyUVC1DyCzcxwe851KXTpCp4xOypvyF7A="
            }
          },
          "68u2KLqtuVY4mZw80ShQDQXIkszw8aRlhLMAC2vxfdU=": {
            "valueMac": {
              "type": "Buffer",
              "data": "K5ctootal+4cVjkzzsGm5cDZk0L+W8G6OL7nZGv24uI="
            }
          },
          "7CHbGeHoeVU099hv5trVlUAsP7qwFPGvTv0lZCUmfw8=": {
            "valueMac": {
              "type": "Buffer",
              "data": "7wh4CGB6PaXArDKfGS1FiZt/IJ+MGnQKSM6pergoesM="
            }
          },
          "7Eu9mFrT6MIJJOeZ7lSPs1XsjRNz46idwNIQ0w0OqC8=": {
            "valueMac": {
              "type": "Buffer",
              "data": "9vrfNWBf1Rlz9XSEI/7lxBqlZ++Cz7QfNqh3psXvM4k="
            }
          },
          "7W542KpRlb5Ur2wMNYiSYXF/tDb7UTTGhc6c3H3qWUA=": {
            "valueMac": {
              "type": "Buffer",
              "data": "o20aQFw5GEfBQ6Dan0xdXLe7I/qIChIdAGJk0EOcQog="
            }
          },
          "7lnfw3NRziezvIPMR3WKdNVGI2ovgB+P0cBgfPwSBQ0=": {
            "valueMac": {
              "type": "Buffer",
              "data": "bA4FDZ2zWi2SR35ngr+f+lCeOJ+x/NOKF8oWt7Gr2vQ="
            }
          },
          "7xVerQi9iWmH6+Y4LQ+QN3Vv9M4J6i2ruPLfyXM17wE=": {
            "valueMac": {
              "type": "Buffer",
              "data": "WMBgUU1hR8uzHIARRPqtACN+vEKs01dssdxMJbvDemw="
            }
          },
          "71vz0u4gkVTQrj0fOo1LTIWjpjyoBqrV2WVTlIv2QP8=": {
            "valueMac": {
              "type": "Buffer",
              "data": "nnOCUSNyv3M6GneUhS1OtIHYpP8U/+zIEYG2fwdAfKs="
            }
          },
          "8L6+KgWvlIhRPN3I9o9jZ9A/lINKUEDihEVGfWepvv0=": {
            "valueMac": {
              "type": "Buffer",
              "data": "amAluU8DqbsAMhZos4uiBa7KlarIj25DjaZb1SRr2/c="
            }
          },
          "8VD7PeUouu+rtcNhf/Ze4PcwYk5bqVCbWGvaxMxFWF0=": {
            "valueMac": {
              "type": "Buffer",
              "data": "U6oKroXTOj09PKYt0H3JQFet+Oyh1hlPUnxdqKkmgQM="
            }
          },
          "8o5k3F4qTbnLzDZuplSWcg5d3pHVNHTkKa4lhot7o38=": {
            "valueMac": {
              "type": "Buffer",
              "data": "dgnt4zkcQwr4wyxWF7/6iOkuttNFja+zf0y3AS+CyUo="
            }
          },
          "8/v3dZSO5ePafAsy3KJNw3li96RymMBQUUCvO2Xa38I=": {
            "valueMac": {
              "type": "Buffer",
              "data": "dTwiFnDFyDuywxXxRUr4QfKQfE+XG261o5hfidANyQI="
            }
          },
          "9YC4mk7qPA0QK9TynlCEiZ57aTFzMCYodKlUx//1GQ0=": {
            "valueMac": {
              "type": "Buffer",
              "data": "zUmvVtedsNA7qOZ8104YRKnd7UTvQ5t5yFqMTYfVlbM="
            }
          },
          "9idUmPv25qhn1yrCt7IcG9SRXcrZw7x9hKD4hrIL8kk=": {
            "valueMac": {
              "type": "Buffer",
              "data": "SmYa4rMDZX4iurxBVQ0vspvf9baCzSqTZQxJP7lNx34="
            }
          },
          "9nocoMqKZQ0OJqpCaKydR6YrC9mmWnDhQINb/smn/wQ=": {
            "valueMac": {
              "type": "Buffer",
              "data": "utPFN+5Pp+dh7/k8GcRJJrrgozxwTmxsBp+/p5G8VoI="
            }
          },
          "97D1vdhUQZJJBUGNy1Rk+1WTFAhDKl4LT+BoFf+KBEU=": {
            "valueMac": {
              "type": "Buffer",
              "data": "SdO3BFigKw+L8Y+I/NIWWuWzD2M59lVG/4bR83JCmNM="
            }
          },
          "+DEgO7gccKBSVjAiiPTmE0Osq+ns+bmmUh2SXGWCR+0=": {
            "valueMac": {
              "type": "Buffer",
              "data": "8+/bDwD0MMDw6Q45P+1aRPvb2EbpdI5p2LWqq2SmM0s="
            }
          },
          "+dQUYViIJmCanN2Sg3M15hEYd/LyLUj1F6+C5vibLuI=": {
            "valueMac": {
              "type": "Buffer",
              "data": "/kBDjSsFvrfsOgYMHnmjU150wO7s42FZx5hZlGliNQU="
            }
          },
          "+2K15eDbmKrHiHFK84eRf3/xEoTNO2Q5EcojOzfVRfY=": {
            "valueMac": {
              "type": "Buffer",
              "data": "DQFQEDGCjrxz7lVpwszVeoduet2i3kkrcl3EeyR2i78="
            }
          },
          "/p0K+IM0g4WupielEHbaxeCAxXM/FfgPaKX3q3l9JGw=": {
            "valueMac": {
              "type": "Buffer",
              "data": "/YVDp18RHBheoL6D+j4gYS/9CoWpjPbKSvIweNeWBMk="
            }
          },
          "/ttcJIAYfmlsnD0puM37pkeKl0fyBRCYtxjMcZI5Dlw=": {
            "valueMac": {
              "type": "Buffer",
              "data": "YO7v70Ufg2f18LP6vDNOOrfNeFKEtxwZnlpzYpCxxC4="
            }
          },
          "/7MSu3T9/F1Z13Q4exN7BLn9U9K4u9xnTHUkdnNCp2s=": {
            "valueMac": {
              "type": "Buffer",
              "data": "hNOEoV1Lw9iSB7srCBp+FEU2uOrGvufb7JqZDtbLRTM="
            }
          },
          "xMnEqCvkOL8UpCAU+inODLjFMZU04caPa50cyu/n1bg=": {
            "valueMac": {
              "type": "Buffer",
              "data": "4fn8PkasE2hrs6IPVzSj5QtXj4piYt9EiHm1XOhgkfQ="
            }
          },
          "mUgxAT2NaJup9+3dWj06jXwmEwIwd4KOng/WOlUQo5Y=": {
            "valueMac": {
              "type": "Buffer",
              "data": "8yjlxeT0lf5tuVjyLis+UsAHx86kApV3KJFK+6hF+eI="
            }
          }
        }
      },
      "regular_low": {
        "version": 30,
        "hash": {
          "type": "Buffer",
          "data": "pS8DE4UcX0VtMuigHBXipfOvt1fLCIssyxzEG75TpiYsZVQXIijbUqFsrOksZP6UkB5j3uREOUO6OfBG/H5cQOIxJcEMGpPt94y7FAxn0XSpEPxc4TTJdWKj2ZLyy6gSOtGud0ZYmJGkrDJ07IIL7evDGRJPMY7HmpwnMOXvftk="
        },
        "indexValueMap": {
          "CPfP2DaOsM64MTgzIgFQx1a132Six2jq2XDNUIfPpfQ=": {
            "valueMac": {
              "type": "Buffer",
              "data": "hWjuql9mF9O4KPv2tGpoFMGc40L1ZNnVns8/5NTod+E="
            }
          },
          "F68/7jM9Uf9FkkGMPYMrY5/7m3HX6g9w7/n8csmInm4=": {
            "valueMac": {
              "type": "Buffer",
              "data": "h0CPFWXEX+fLsk4oB/3EDVjWhfuNi7IWsndvYOh7szk="
            }
          },
          "H2l75c2DCZTj8mggBKLxuqmR0hWW1ReCF9b19bk+dkc=": {
            "valueMac": {
              "type": "Buffer",
              "data": "IsFfwJ0znFx9q2mndbmwNnRztXUm9JEQWQix8m9zwMg="
            }
          },
          "I7+DNR60iH0JaxSxjwi7Zlk6OGlsR4/RMTyrcgKvw8c=": {
            "valueMac": {
              "type": "Buffer",
              "data": "o0lYuEVVtCC3Atk3r9/UJgNsYPRhnDoqKEh4CLz0Yu4="
            }
          },
          "JhO4R0vVHTHzuIsSG8ZFzx1q+quEOgztqdHWhM0CmjA=": {
            "valueMac": {
              "type": "Buffer",
              "data": "iGv6Txyslv0hhvVTvKIQjhRmecbw3YzVzuN7yVJV4wg="
            }
          },
          "MNmX5a+rL3BxhoD1e77EQehGfYYukWdunFHuNDbn4Qs=": {
            "valueMac": {
              "type": "Buffer",
              "data": "9ql+gAChrMC3hYF+ySES/gFNUJ5+4eskOrkNVFLgj6E="
            }
          },
          "TRQlFxygJ7j2zcbjcrFQJCzT575aPTGNjMgEDVi61tA=": {
            "valueMac": {
              "type": "Buffer",
              "data": "QdeMrxHStekutqxVQNLaOPVgEarCadejekKAGKruYs4="
            }
          },
          "XOVd8Zfj1OXIAbxZuPjBrYq3qSkwZ4y/p3XQV13nMk8=": {
            "valueMac": {
              "type": "Buffer",
              "data": "ibWgr2J3pporjDl1Ht+RZ7wAf1Vqlk18HAawZRi4uUo="
            }
          },
          "Z7RMfatIntj297CBoKTt020xw6AfKZ2sW6tRgYS/C4I=": {
            "valueMac": {
              "type": "Buffer",
              "data": "xLdz435xaJv2/fsEpP6uywYIezP/8qg0/It6Tk9iX3Q="
            }
          },
          "cwYWL8WmVgpNOiOs+EJ6OzGNMx/JGGf1/S7Ex1jr9p0=": {
            "valueMac": {
              "type": "Buffer",
              "data": "+RDfv9wFMohFtitZ4p6JcgFxHcELkxtQ24LHRM2+gfw="
            }
          },
          "gechq5+DV2MxkmYLhez2Jqvzf37mNSlFdV1cUg6yzZs=": {
            "valueMac": {
              "type": "Buffer",
              "data": "9Za1M8Drg346hsINl5yoNFjzj3Qor9blr+64P1SjPSM="
            }
          },
          "pCRYIrwzWgunV49rQsoN6ObbgsKSy7PMwrg1EURpGj0=": {
            "valueMac": {
              "type": "Buffer",
              "data": "rAJPBvBQZVtzCikoQGPgj83ZQY/MCnc+9QARt/9m/Rw="
            }
          },
          "tUaYg7EQZSnGRV11nWZE+2ZuMHh4uUzpNW1lZ6rP3uE=": {
            "valueMac": {
              "type": "Buffer",
              "data": "gNG7R6GIscJHS6xSyB9+Yx5EwZAWJDGewAfPjOsb2BU="
            }
          },
          "vKmJvgqPrBWAUJDUxmPnQoZOiKDMNigIZUHw3vv7u9o=": {
            "valueMac": {
              "type": "Buffer",
              "data": "brkl6wLilrd7hf6condUz6Rt2/2iXx+fIg81pqJUsnk="
            }
          },
          "wUfJjmoxyVbvB++hBhKh8EilBzUoYoSj9YACc4swU90=": {
            "valueMac": {
              "type": "Buffer",
              "data": "zPQxjJm0TKTCXPIqL1ZuVQ4aJumHaSHRQn56BFfKxoU="
            }
          },
          "wi/ItFXm3pQU245FNsiHFrrWqk8ZL01Y1iIyNluV5XM=": {
            "valueMac": {
              "type": "Buffer",
              "data": "UgInnaq8cdiAE9T/ekxpiFco5tBosyu/7A7I+Xi1V04="
            }
          },
          "x7BTAFmS6HZ+8ROE5bWmIqmz2wNGg0Z4X0vrLKnFjOs=": {
            "valueMac": {
              "type": "Buffer",
              "data": "Wyt/yV0sg+yodDZrcU6QQfH7SZGpZcpGqL61uAFaag4="
            }
          },
          "9ni+gupOZxlea0nAhfz0nBTmB+uAi0Cx61T8FNklUCQ=": {
            "valueMac": {
              "type": "Buffer",
              "data": "LEIwOTSfChoBdr4hwV8rp3HkxhxC4IXj5Ag8rgfe+Fs="
            }
          },
          "Wc3fhwpO/L+wB5/yZMsU6ay4nPB0/rHQd/PKjcDgyUg=": {
            "valueMac": {
              "type": "Buffer",
              "data": "1/WjKxJkWNnUhD+baGrgZlWD/kkY1/gpXTCHy0SDmMk="
            }
          },
          "YlFSyBKK9eXDx7mMBjKcSYTc2DXy+Ho0S9kT8tyHE9E=": {
            "valueMac": {
              "type": "Buffer",
              "data": "lpF3dsrfKP8lf8qPujvT9Lz2pk1fvoKp4exWCDp8P+I="
            }
          }
        }
      },
      "critical_unblock_low": null,
      "regular": {
        "version": 15,
        "hash": {
          "type": "Buffer",
          "data": "2RUQ3GemOOo/FFHZKDFzSZzgVf/hphZddiUJ3F15Dh8jUnQ4/6Wkgl1o3aGLmDTmqfjvLge/mZPwSGJSBktMg9pwpQQN0vGsPIRxfAUeU0jhGi+OFYnDoqc8547kxP7kJ8QeUOGjUQYZJBsqdYkhDpabzd7ehO0D4Q3aYgctCvw="
        },
        "indexValueMap": {
          "TyS9u/cVmKi00HupOtlb6IGRfYDEeeo+dctNZT+/e5c=": {
            "valueMac": {
              "type": "Buffer",
              "data": "YQtYhX0KbEzYUsliLMcbPD43FzGi33e0k4zT0fMcD8A="
            }
          },
          "7GLi84Numcve6rxuO8Uc80m5e3Z1LhcQ88iUXNv9omg=": {
            "valueMac": {
              "type": "Buffer",
              "data": "lw6GF5zplzbIbd3QbtveQk3L0iCxmBi0KpgN6Lg4cwE="
            }
          }
        }
      },
      "critical_block": {
        "version": 16,
        "hash": {
          "type": "Buffer",
          "data": "WZ0vXrEVZ5GkByewXTIOB0wCoboycp3eyp63EAg26MLxb+H3rZwBskFsTgJ2GPe1xWo7Y/Dz5MOb17m2Hq1YIGhrw5l6P+YYlWmDqWAYqGf9tWofvuLhF08oT1Sn9kq/LqYBuvU9VLC7IJ4JfcUfTOEBcQ1rXQcdIVGX+jwe6rc="
        },
        "indexValueMap": {
          "5H51UtNffOzOFXVQ/9RFo/KKujEp4snta4l6K6eYB4A=": {
            "valueMac": {
              "type": "Buffer",
              "data": "DpqnENXC50ULpl+LlmfUhQR97B13UnZe6F++o5nargI="
            }
          },
          "BJSqoZOULJsWYR+YKrLzIH31/hBW95kTazvjdu2Ikdg=": {
            "valueMac": {
              "type": "Buffer",
              "data": "8sKj7GkSg0HmswkaZ/dh/AqtCC8KEZ5vpt/2Eye39fI="
            }
          },
          "3r5av3UZYEWclCdVKZQC6eyGAHXHLpnakEuSwg2AO5A=": {
            "valueMac": {
              "type": "Buffer",
              "data": "+Wg1r4ZNo6xwRbGOLAHwAbyzNGX7EOr4w4+2Z0LKduE="
            }
          }
        }
      }
    }
  }
}